[
  {
    "_id": "698ec0002d2b92cf4e8efc4c",
    "Month": "2025-04",
    "State": "Maharashtra",
    "RTO": "MAH-RTO-1",
    "Staff - Total": 67,
    "Staff - Counter": 24,
    "Staff - Field Enforcement": 9,
    "Staff - Back Office": 18,
    "Staff - Call Center": 16,
    "Anomalies Detected": 1
  },
  {
    "_id": "698ec0002d2b92cf4e8efc4d",
    "Month": "2025-05",
    "State": "Maharashtra",
    "RTO": "MAH-RTO-1",
    "Staff - Total": 230,
    "Staff - Counter": 78,
    "Staff - Field Enforcement": 56,
    "Staff - Back Office": 69,
    "Staff - Call Center": 27,
    "Anomalies Detected": 7
  },
  {
    "_id": "698ec0002d2b92cf4e8efc4e",
    "Month": "2025-06",
    "State": "Maharashtra",
    "RTO": "MAH-RTO-1",
    "Staff - Total": 72,
    "Staff - Counter": 20,
    "Staff - Field Enforcement": 17,
    "Staff - Back Office": 26,
    "Staff - Call Center": 9,
    "Anomalies Detected": 3
  },
  {
    "_id": "698ec0002d2b92cf4e8efc4f",
    "Month": "2025-07",
    "State": "Maharashtra",
    "RTO": "MAH-RTO-1",
    "Staff - Total": 219,
    "Staff - Counter": 74,
    "Staff - Field Enforcement": 49,
    "Staff - Back Office": 70,
    "Staff - Call Center": 26,
    "Anomalies Detected": 9
  },
  {
    "_id": "698ec0002d2b92cf4e8efc50",
    "Month": "2025-08",
    "State": "Maharashtra",
    "RTO": "MAH-RTO-1",
    "Staff - Total": 76,
    "Staff - Counter": 22,
    "Staff - Field Enforcement": 19,
    "Staff - Back Office": 16,
    "Staff - Call Center": 19,
    "Anomalies Detected": 8
  },
  {
    "_id": "698ec0002d2b92cf4e8efc51",
    "Month": "2025-09",
    "State": "Maharashtra",
    "RTO": "MAH-RTO-1",
    "Staff - Total": 131,
    "Staff - Counter": 38,
    "Staff - Field Enforcement": 28,
    "Staff - Back Office": 46,
    "Staff - Call Center": 19,
    "Anomalies Detected": 6
  },
  {
    "_id": "698ec0002d2b92cf4e8efc52",
    "Month": "2025-10",
    "State": "Maharashtra",
    "RTO": "MAH-RTO-1",
    "Staff - Total": 111,
    "Staff - Counter": 41,
    "Staff - Field Enforcement": 24,
    "Staff - Back Office": 37,
    "Staff - Call Center": 9,
    "Anomalies Detected": 12
  },
  {
    "_id": "698ec0002d2b92cf4e8efc53",
    "Month": "2025-11",
    "State": "Maharashtra",
    "RTO": "MAH-RTO-1",
    "Staff - Total": 219,
    "Staff - Counter": 76,
    "Staff - Field Enforcement": 54,
    "Staff - Back Office": 77,
    "Staff - Call Center": 12,
    "Anomalies Detected": 2
  },
  {
    "_id": "698ec0002d2b92cf4e8efc54",
    "Month": "2025-12",
    "State": "Maharashtra",
    "RTO": "MAH-RTO-1",
    "Staff - Total": 98,
    "Staff - Counter": 31,
    "Staff - Field Enforcement": 27,
    "Staff - Back Office": 40,
    "Staff - Call Center": 3,
    "Anomalies Detected": 3
  },
  {
    "_id": "698ec0002d2b92cf4e8efc55",
    "Month": "2026-01",
    "State": "Maharashtra",
    "RTO": "MAH-RTO-1",
    "Staff - Total": 189,
    "Staff - Counter": 61,
    "Staff - Field Enforcement": 46,
    "Staff - Back Office": 54,
    "Staff - Call Center": 28,
    "Anomalies Detected": 7
  },
  {
    "_id": "698ec0002d2b92cf4e8efc56",
    "Month": "2025-04",
    "State": "Maharashtra",
    "RTO": "MAH-RTO-2",
    "Staff - Total": 66,
    "Staff - Counter": 16,
    "Staff - Field Enforcement": 22,
    "Staff - Back Office": 12,
    "Staff - Call Center": 16,
    "Anomalies Detected": 3
  },
  {
    "_id": "698ec0002d2b92cf4e8efc57",
    "Month": "2025-05",
    "State": "Maharashtra",
    "RTO": "MAH-RTO-2",
    "Staff - Total": 201,
    "Staff - Counter": 75,
    "Staff - Field Enforcement": 50,
    "Staff - Back Office": 55,
    "Staff - Call Center": 21,
    "Anomalies Detected": 0
  },
  {
    "_id": "698ec0002d2b92cf4e8efc58",
    "Month": "2025-06",
    "State": "Maharashtra",
    "RTO": "MAH-RTO-2",
    "Staff - Total": 214,
    "Staff - Counter": 73,
    "Staff - Field Enforcement": 50,
    "Staff - Back Office": 65,
    "Staff - Call Center": 26,
    "Anomalies Detected": 0
  },
  {
    "_id": "698ec0002d2b92cf4e8efc59",
    "Month": "2025-07",
    "State": "Maharashtra",
    "RTO": "MAH-RTO-2",
    "Staff - Total": 237,
    "Staff - Counter": 87,
    "Staff - Field Enforcement": 59,
    "Staff - Back Office": 72,
    "Staff - Call Center": 19,
    "Anomalies Detected": 7
  },
  {
    "_id": "698ec0002d2b92cf4e8efc5a",
    "Month": "2025-08",
    "State": "Maharashtra",
    "RTO": "MAH-RTO-2",
    "Staff - Total": 161,
    "Staff - Counter": 54,
    "Staff - Field Enforcement": 37,
    "Staff - Back Office": 45,
    "Staff - Call Center": 25,
    "Anomalies Detected": 7
  },
  {
    "_id": "698ec0002d2b92cf4e8efc5b",
    "Month": "2025-09",
    "State": "Maharashtra",
    "RTO": "MAH-RTO-2",
    "Staff - Total": 167,
    "Staff - Counter": 57,
    "Staff - Field Enforcement": 38,
    "Staff - Back Office": 39,
    "Staff - Call Center": 33,
    "Anomalies Detected": 11
  },
  {
    "_id": "698ec0002d2b92cf4e8efc5c",
    "Month": "2025-10",
    "State": "Maharashtra",
    "RTO": "MAH-RTO-2",
    "Staff - Total": 113,
    "Staff - Counter": 41,
    "Staff - Field Enforcement": 28,
    "Staff - Back Office": 39,
    "Staff - Call Center": 5,
    "Anomalies Detected": 8
  },
  {
    "_id": "698ec0002d2b92cf4e8efc5d",
    "Month": "2025-11",
    "State": "Maharashtra",
    "RTO": "MAH-RTO-2",
    "Staff - Total": 164,
    "Staff - Counter": 61,
    "Staff - Field Enforcement": 46,
    "Staff - Back Office": 53,
    "Staff - Call Center": 4,
    "Anomalies Detected": 11
  },
  {
    "_id": "698ec0002d2b92cf4e8efc5e",
    "Month": "2025-12",
    "State": "Maharashtra",
    "RTO": "MAH-RTO-2",
    "Staff - Total": 205,
    "Staff - Counter": 81,
    "Staff - Field Enforcement": 55,
    "Staff - Back Office": 65,
    "Staff - Call Center": 4,
    "Anomalies Detected": 5
  },
  {
    "_id": "698ec0002d2b92cf4e8efc5f",
    "Month": "2026-01",
    "State": "Maharashtra",
    "RTO": "MAH-RTO-2",
    "Staff - Total": 138,
    "Staff - Counter": 48,
    "Staff - Field Enforcement": 33,
    "Staff - Back Office": 44,
    "Staff - Call Center": 13,
    "Anomalies Detected": 8
  },
  {
    "_id": "698ec0002d2b92cf4e8efc60",
    "Month": "2025-04",
    "State": "Maharashtra",
    "RTO": "MAH-RTO-3",
    "Staff - Total": 143,
    "Staff - Counter": 49,
    "Staff - Field Enforcement": 26,
    "Staff - Back Office": 51,
    "Staff - Call Center": 17,
    "Anomalies Detected": 8
  },
  {
    "_id": "698ec0002d2b92cf4e8efc61",
    "Month": "2025-05",
    "State": "Maharashtra",
    "RTO": "MAH-RTO-3",
    "Staff - Total": 205,
    "Staff - Counter": 74,
    "Staff - Field Enforcement": 57,
    "Staff - Back Office": 63,
    "Staff - Call Center": 11,
    "Anomalies Detected": 2
  },
  {
    "_id": "698ec0002d2b92cf4e8efc62",
    "Month": "2025-06",
    "State": "Maharashtra",
    "RTO": "MAH-RTO-3",
    "Staff - Total": 132,
    "Staff - Counter": 39,
    "Staff - Field Enforcement": 42,
    "Staff - Back Office": 45,
    "Staff - Call Center": 6,
    "Anomalies Detected": 1
  },
  {
    "_id": "698ec0002d2b92cf4e8efc63",
    "Month": "2025-07",
    "State": "Maharashtra",
    "RTO": "MAH-RTO-3",
    "Staff - Total": 123,
    "Staff - Counter": 50,
    "Staff - Field Enforcement": 26,
    "Staff - Back Office": 35,
    "Staff - Call Center": 12,
    "Anomalies Detected": 9
  },
  {
    "_id": "698ec0002d2b92cf4e8efc64",
    "Month": "2025-08",
    "State": "Maharashtra",
    "RTO": "MAH-RTO-3",
    "Staff - Total": 74,
    "Staff - Counter": 16,
    "Staff - Field Enforcement": 20,
    "Staff - Back Office": 24,
    "Staff - Call Center": 14,
    "Anomalies Detected": 9
  },
  {
    "_id": "698ec0002d2b92cf4e8efc65",
    "Month": "2025-09",
    "State": "Maharashtra",
    "RTO": "MAH-RTO-3",
    "Staff - Total": 85,
    "Staff - Counter": 21,
    "Staff - Field Enforcement": 27,
    "Staff - Back Office": 22,
    "Staff - Call Center": 15,
    "Anomalies Detected": 9
  },
  {
    "_id": "698ec0002d2b92cf4e8efc66",
    "Month": "2025-10",
    "State": "Maharashtra",
    "RTO": "MAH-RTO-3",
    "Staff - Total": 82,
    "Staff - Counter": 22,
    "Staff - Field Enforcement": 16,
    "Staff - Back Office": 26,
    "Staff - Call Center": 18,
    "Anomalies Detected": 2
  },
  {
    "_id": "698ec0002d2b92cf4e8efc67",
    "Month": "2025-11",
    "State": "Maharashtra",
    "RTO": "MAH-RTO-3",
    "Staff - Total": 137,
    "Staff - Counter": 51,
    "Staff - Field Enforcement": 31,
    "Staff - Back Office": 35,
    "Staff - Call Center": 20,
    "Anomalies Detected": 10
  },
  {
    "_id": "698ec0002d2b92cf4e8efc68",
    "Month": "2025-12",
    "State": "Maharashtra",
    "RTO": "MAH-RTO-3",
    "Staff - Total": 179,
    "Staff - Counter": 64,
    "Staff - Field Enforcement": 43,
    "Staff - Back Office": 53,
    "Staff - Call Center": 19,
    "Anomalies Detected": 2
  },
  {
    "_id": "698ec0002d2b92cf4e8efc69",
    "Month": "2026-01",
    "State": "Maharashtra",
    "RTO": "MAH-RTO-3",
    "Staff - Total": 107,
    "Staff - Counter": 42,
    "Staff - Field Enforcement": 25,
    "Staff - Back Office": 26,
    "Staff - Call Center": 14,
    "Anomalies Detected": 7
  },
  {
    "_id": "698ec0002d2b92cf4e8efc6a",
    "Month": "2025-04",
    "State": "Gujarat",
    "RTO": "GUJ-RTO-1",
    "Staff - Total": 85,
    "Staff - Counter": 32,
    "Staff - Field Enforcement": 15,
    "Staff - Back Office": 21,
    "Staff - Call Center": 17,
    "Anomalies Detected": 0
  },
  {
    "_id": "698ec0002d2b92cf4e8efc6b",
    "Month": "2025-05",
    "State": "Gujarat",
    "RTO": "GUJ-RTO-1",
    "Staff - Total": 166,
    "Staff - Counter": 57,
    "Staff - Field Enforcement": 38,
    "Staff - Back Office": 53,
    "Staff - Call Center": 18,
    "Anomalies Detected": 4
  },
  {
    "_id": "698ec0002d2b92cf4e8efc6c",
    "Month": "2025-06",
    "State": "Gujarat",
    "RTO": "GUJ-RTO-1",
    "Staff - Total": 127,
    "Staff - Counter": 36,
    "Staff - Field Enforcement": 30,
    "Staff - Back Office": 37,
    "Staff - Call Center": 24,
    "Anomalies Detected": 4
  },
  {
    "_id": "698ec0002d2b92cf4e8efc6d",
    "Month": "2025-07",
    "State": "Gujarat",
    "RTO": "GUJ-RTO-1",
    "Staff - Total": 176,
    "Staff - Counter": 58,
    "Staff - Field Enforcement": 42,
    "Staff - Back Office": 50,
    "Staff - Call Center": 26,
    "Anomalies Detected": 4
  },
  {
    "_id": "698ec0002d2b92cf4e8efc6e",
    "Month": "2025-08",
    "State": "Gujarat",
    "RTO": "GUJ-RTO-1",
    "Staff - Total": 146,
    "Staff - Counter": 47,
    "Staff - Field Enforcement": 42,
    "Staff - Back Office": 46,
    "Staff - Call Center": 11,
    "Anomalies Detected": 3
  },
  {
    "_id": "698ec0002d2b92cf4e8efc6f",
    "Month": "2025-09",
    "State": "Gujarat",
    "RTO": "GUJ-RTO-1",
    "Staff - Total": 115,
    "Staff - Counter": 40,
    "Staff - Field Enforcement": 29,
    "Staff - Back Office": 40,
    "Staff - Call Center": 6,
    "Anomalies Detected": 12
  },
  {
    "_id": "698ec0002d2b92cf4e8efc70",
    "Month": "2025-10",
    "State": "Gujarat",
    "RTO": "GUJ-RTO-1",
    "Staff - Total": 201,
    "Staff - Counter": 74,
    "Staff - Field Enforcement": 50,
    "Staff - Back Office": 67,
    "Staff - Call Center": 10,
    "Anomalies Detected": 9
  },
  {
    "_id": "698ec0002d2b92cf4e8efc71",
    "Month": "2025-11",
    "State": "Gujarat",
    "RTO": "GUJ-RTO-1",
    "Staff - Total": 218,
    "Staff - Counter": 77,
    "Staff - Field Enforcement": 53,
    "Staff - Back Office": 67,
    "Staff - Call Center": 21,
    "Anomalies Detected": 7
  },
  {
    "_id": "698ec0002d2b92cf4e8efc72",
    "Month": "2025-12",
    "State": "Gujarat",
    "RTO": "GUJ-RTO-1",
    "Staff - Total": 222,
    "Staff - Counter": 86,
    "Staff - Field Enforcement": 55,
    "Staff - Back Office": 64,
    "Staff - Call Center": 17,
    "Anomalies Detected": 2
  },
  {
    "_id": "698ec0002d2b92cf4e8efc73",
    "Month": "2026-01",
    "State": "Gujarat",
    "RTO": "GUJ-RTO-1",
    "Staff - Total": 230,
    "Staff - Counter": 74,
    "Staff - Field Enforcement": 59,
    "Staff - Back Office": 64,
    "Staff - Call Center": 33,
    "Anomalies Detected": 8
  },
  {
    "_id": "698ec0002d2b92cf4e8efc74",
    "Month": "2025-04",
    "State": "Gujarat",
    "RTO": "GUJ-RTO-2",
    "Staff - Total": 224,
    "Staff - Counter": 71,
    "Staff - Field Enforcement": 56,
    "Staff - Back Office": 72,
    "Staff - Call Center": 25,
    "Anomalies Detected": 8
  },
  {
    "_id": "698ec0002d2b92cf4e8efc75",
    "Month": "2025-05",
    "State": "Gujarat",
    "RTO": "GUJ-RTO-2",
    "Staff - Total": 105,
    "Staff - Counter": 46,
    "Staff - Field Enforcement": 24,
    "Staff - Back Office": 32,
    "Staff - Call Center": 3,
    "Anomalies Detected": 2
  },
  {
    "_id": "698ec0002d2b92cf4e8efc76",
    "Month": "2025-06",
    "State": "Gujarat",
    "RTO": "GUJ-RTO-2",
    "Staff - Total": 152,
    "Staff - Counter": 56,
    "Staff - Field Enforcement": 39,
    "Staff - Back Office": 50,
    "Staff - Call Center": 7,
    "Anomalies Detected": 8
  },
  {
    "_id": "698ec0002d2b92cf4e8efc77",
    "Month": "2025-07",
    "State": "Gujarat",
    "RTO": "GUJ-RTO-2",
    "Staff - Total": 214,
    "Staff - Counter": 83,
    "Staff - Field Enforcement": 55,
    "Staff - Back Office": 74,
    "Staff - Call Center": 3,
    "Anomalies Detected": 2
  },
  {
    "_id": "698ec0002d2b92cf4e8efc78",
    "Month": "2025-08",
    "State": "Gujarat",
    "RTO": "GUJ-RTO-2",
    "Staff - Total": 199,
    "Staff - Counter": 60,
    "Staff - Field Enforcement": 60,
    "Staff - Back Office": 56,
    "Staff - Call Center": 23,
    "Anomalies Detected": 2
  },
  {
    "_id": "698ec0002d2b92cf4e8efc79",
    "Month": "2025-09",
    "State": "Gujarat",
    "RTO": "GUJ-RTO-2",
    "Staff - Total": 232,
    "Staff - Counter": 81,
    "Staff - Field Enforcement": 62,
    "Staff - Back Office": 66,
    "Staff - Call Center": 23,
    "Anomalies Detected": 4
  },
  {
    "_id": "698ec0002d2b92cf4e8efc7a",
    "Month": "2025-10",
    "State": "Gujarat",
    "RTO": "GUJ-RTO-2",
    "Staff - Total": 232,
    "Staff - Counter": 79,
    "Staff - Field Enforcement": 64,
    "Staff - Back Office": 71,
    "Staff - Call Center": 18,
    "Anomalies Detected": 7
  },
  {
    "_id": "698ec0002d2b92cf4e8efc7b",
    "Month": "2025-11",
    "State": "Gujarat",
    "RTO": "GUJ-RTO-2",
    "Staff - Total": 65,
    "Staff - Counter": 11,
    "Staff - Field Enforcement": 15,
    "Staff - Back Office": 21,
    "Staff - Call Center": 18,
    "Anomalies Detected": 6
  },
  {
    "_id": "698ec0002d2b92cf4e8efc7c",
    "Month": "2025-12",
    "State": "Gujarat",
    "RTO": "GUJ-RTO-2",
    "Staff - Total": 213,
    "Staff - Counter": 79,
    "Staff - Field Enforcement": 51,
    "Staff - Back Office": 64,
    "Staff - Call Center": 19,
    "Anomalies Detected": 10
  },
  {
    "_id": "698ec0002d2b92cf4e8efc7d",
    "Month": "2026-01",
    "State": "Gujarat",
    "RTO": "GUJ-RTO-2",
    "Staff - Total": 112,
    "Staff - Counter": 27,
    "Staff - Field Enforcement": 30,
    "Staff - Back Office": 31,
    "Staff - Call Center": 24,
    "Anomalies Detected": 11
  },
  {
    "_id": "698ec0002d2b92cf4e8efc7e",
    "Month": "2025-04",
    "State": "Gujarat",
    "RTO": "GUJ-RTO-3",
    "Staff - Total": 117,
    "Staff - Counter": 42,
    "Staff - Field Enforcement": 34,
    "Staff - Back Office": 40,
    "Staff - Call Center": 3,
    "Anomalies Detected": 5
  },
  {
    "_id": "698ec0002d2b92cf4e8efc7f",
    "Month": "2025-05",
    "State": "Gujarat",
    "RTO": "GUJ-RTO-3",
    "Staff - Total": 196,
    "Staff - Counter": 72,
    "Staff - Field Enforcement": 52,
    "Staff - Back Office": 58,
    "Staff - Call Center": 14,
    "Anomalies Detected": 11
  },
  {
    "_id": "698ec0002d2b92cf4e8efc80",
    "Month": "2025-06",
    "State": "Gujarat",
    "RTO": "GUJ-RTO-3",
    "Staff - Total": 197,
    "Staff - Counter": 65,
    "Staff - Field Enforcement": 52,
    "Staff - Back Office": 58,
    "Staff - Call Center": 22,
    "Anomalies Detected": 7
  },
  {
    "_id": "698ec0002d2b92cf4e8efc81",
    "Month": "2025-07",
    "State": "Gujarat",
    "RTO": "GUJ-RTO-3",
    "Staff - Total": 125,
    "Staff - Counter": 35,
    "Staff - Field Enforcement": 34,
    "Staff - Back Office": 34,
    "Staff - Call Center": 22,
    "Anomalies Detected": 11
  },
  {
    "_id": "698ec0002d2b92cf4e8efc82",
    "Month": "2025-08",
    "State": "Gujarat",
    "RTO": "GUJ-RTO-3",
    "Staff - Total": 122,
    "Staff - Counter": 48,
    "Staff - Field Enforcement": 25,
    "Staff - Back Office": 36,
    "Staff - Call Center": 13,
    "Anomalies Detected": 0
  },
  {
    "_id": "698ec0002d2b92cf4e8efc83",
    "Month": "2025-09",
    "State": "Gujarat",
    "RTO": "GUJ-RTO-3",
    "Staff - Total": 74,
    "Staff - Counter": 27,
    "Staff - Field Enforcement": 23,
    "Staff - Back Office": 15,
    "Staff - Call Center": 9,
    "Anomalies Detected": 5
  },
  {
    "_id": "698ec0002d2b92cf4e8efc84",
    "Month": "2025-10",
    "State": "Gujarat",
    "RTO": "GUJ-RTO-3",
    "Staff - Total": 88,
    "Staff - Counter": 35,
    "Staff - Field Enforcement": 21,
    "Staff - Back Office": 25,
    "Staff - Call Center": 7,
    "Anomalies Detected": 9
  },
  {
    "_id": "698ec0002d2b92cf4e8efc85",
    "Month": "2025-11",
    "State": "Gujarat",
    "RTO": "GUJ-RTO-3",
    "Staff - Total": 86,
    "Staff - Counter": 31,
    "Staff - Field Enforcement": 23,
    "Staff - Back Office": 28,
    "Staff - Call Center": 4,
    "Anomalies Detected": 12
  },
  {
    "_id": "698ec0002d2b92cf4e8efc86",
    "Month": "2025-12",
    "State": "Gujarat",
    "RTO": "GUJ-RTO-3",
    "Staff - Total": 119,
    "Staff - Counter": 46,
    "Staff - Field Enforcement": 34,
    "Staff - Back Office": 36,
    "Staff - Call Center": 3,
    "Anomalies Detected": 7
  },
  {
    "_id": "698ec0002d2b92cf4e8efc87",
    "Month": "2026-01",
    "State": "Gujarat",
    "RTO": "GUJ-RTO-3",
    "Staff - Total": 83,
    "Staff - Counter": 28,
    "Staff - Field Enforcement": 21,
    "Staff - Back Office": 19,
    "Staff - Call Center": 15,
    "Anomalies Detected": 10
  },
  {
    "_id": "698ec0002d2b92cf4e8efc88",
    "Month": "2025-04",
    "State": "Delhi",
    "RTO": "DEL-RTO-1",
    "Staff - Total": 176,
    "Staff - Counter": 54,
    "Staff - Field Enforcement": 46,
    "Staff - Back Office": 53,
    "Staff - Call Center": 23,
    "Anomalies Detected": 8
  },
  {
    "_id": "698ec0002d2b92cf4e8efc89",
    "Month": "2025-05",
    "State": "Delhi",
    "RTO": "DEL-RTO-1",
    "Staff - Total": 98,
    "Staff - Counter": 36,
    "Staff - Field Enforcement": 24,
    "Staff - Back Office": 31,
    "Staff - Call Center": 7,
    "Anomalies Detected": 5
  },
  {
    "_id": "698ec0002d2b92cf4e8efc8a",
    "Month": "2025-06",
    "State": "Delhi",
    "RTO": "DEL-RTO-1",
    "Staff - Total": 121,
    "Staff - Counter": 38,
    "Staff - Field Enforcement": 27,
    "Staff - Back Office": 33,
    "Staff - Call Center": 23,
    "Anomalies Detected": 6
  },
  {
    "_id": "698ec0002d2b92cf4e8efc8b",
    "Month": "2025-07",
    "State": "Delhi",
    "RTO": "DEL-RTO-1",
    "Staff - Total": 199,
    "Staff - Counter": 70,
    "Staff - Field Enforcement": 48,
    "Staff - Back Office": 57,
    "Staff - Call Center": 24,
    "Anomalies Detected": 1
  },
  {
    "_id": "698ec0002d2b92cf4e8efc8c",
    "Month": "2025-08",
    "State": "Delhi",
    "RTO": "DEL-RTO-1",
    "Staff - Total": 82,
    "Staff - Counter": 41,
    "Staff - Field Enforcement": 17,
    "Staff - Back Office": 21,
    "Staff - Call Center": 3,
    "Anomalies Detected": 5
  },
  {
    "_id": "698ec0002d2b92cf4e8efc8d",
    "Month": "2025-09",
    "State": "Delhi",
    "RTO": "DEL-RTO-1",
    "Staff - Total": 210,
    "Staff - Counter": 75,
    "Staff - Field Enforcement": 46,
    "Staff - Back Office": 67,
    "Staff - Call Center": 22,
    "Anomalies Detected": 11
  },
  {
    "_id": "698ec0002d2b92cf4e8efc8e",
    "Month": "2025-10",
    "State": "Delhi",
    "RTO": "DEL-RTO-1",
    "Staff - Total": 96,
    "Staff - Counter": 38,
    "Staff - Field Enforcement": 23,
    "Staff - Back Office": 26,
    "Staff - Call Center": 9,
    "Anomalies Detected": 0
  },
  {
    "_id": "698ec0002d2b92cf4e8efc8f",
    "Month": "2025-11",
    "State": "Delhi",
    "RTO": "DEL-RTO-1",
    "Staff - Total": 207,
    "Staff - Counter": 75,
    "Staff - Field Enforcement": 55,
    "Staff - Back Office": 64,
    "Staff - Call Center": 13,
    "Anomalies Detected": 9
  },
  {
    "_id": "698ec0002d2b92cf4e8efc90",
    "Month": "2025-12",
    "State": "Delhi",
    "RTO": "DEL-RTO-1",
    "Staff - Total": 85,
    "Staff - Counter": 32,
    "Staff - Field Enforcement": 26,
    "Staff - Back Office": 26,
    "Staff - Call Center": 3,
    "Anomalies Detected": 3
  },
  {
    "_id": "698ec0002d2b92cf4e8efc91",
    "Month": "2026-01",
    "State": "Delhi",
    "RTO": "DEL-RTO-1",
    "Staff - Total": 138,
    "Staff - Counter": 52,
    "Staff - Field Enforcement": 35,
    "Staff - Back Office": 42,
    "Staff - Call Center": 9,
    "Anomalies Detected": 4
  },
  {
    "_id": "698ec0002d2b92cf4e8efc92",
    "Month": "2025-04",
    "State": "Delhi",
    "RTO": "DEL-RTO-2",
    "Staff - Total": 95,
    "Staff - Counter": 26,
    "Staff - Field Enforcement": 23,
    "Staff - Back Office": 29,
    "Staff - Call Center": 17,
    "Anomalies Detected": 8
  },
  {
    "_id": "698ec0002d2b92cf4e8efc93",
    "Month": "2025-05",
    "State": "Delhi",
    "RTO": "DEL-RTO-2",
    "Staff - Total": 83,
    "Staff - Counter": 30,
    "Staff - Field Enforcement": 20,
    "Staff - Back Office": 28,
    "Staff - Call Center": 5,
    "Anomalies Detected": 7
  },
  {
    "_id": "698ec0002d2b92cf4e8efc94",
    "Month": "2025-06",
    "State": "Delhi",
    "RTO": "DEL-RTO-2",
    "Staff - Total": 124,
    "Staff - Counter": 44,
    "Staff - Field Enforcement": 25,
    "Staff - Back Office": 46,
    "Staff - Call Center": 9,
    "Anomalies Detected": 4
  },
  {
    "_id": "698ec0002d2b92cf4e8efc95",
    "Month": "2025-07",
    "State": "Delhi",
    "RTO": "DEL-RTO-2",
    "Staff - Total": 161,
    "Staff - Counter": 55,
    "Staff - Field Enforcement": 38,
    "Staff - Back Office": 45,
    "Staff - Call Center": 23,
    "Anomalies Detected": 3
  },
  {
    "_id": "698ec0002d2b92cf4e8efc96",
    "Month": "2025-08",
    "State": "Delhi",
    "RTO": "DEL-RTO-2",
    "Staff - Total": 163,
    "Staff - Counter": 63,
    "Staff - Field Enforcement": 42,
    "Staff - Back Office": 48,
    "Staff - Call Center": 10,
    "Anomalies Detected": 12
  },
  {
    "_id": "698ec0002d2b92cf4e8efc97",
    "Month": "2025-09",
    "State": "Delhi",
    "RTO": "DEL-RTO-2",
    "Staff - Total": 209,
    "Staff - Counter": 73,
    "Staff - Field Enforcement": 51,
    "Staff - Back Office": 64,
    "Staff - Call Center": 21,
    "Anomalies Detected": 9
  },
  {
    "_id": "698ec0002d2b92cf4e8efc98",
    "Month": "2025-10",
    "State": "Delhi",
    "RTO": "DEL-RTO-2",
    "Staff - Total": 163,
    "Staff - Counter": 58,
    "Staff - Field Enforcement": 41,
    "Staff - Back Office": 51,
    "Staff - Call Center": 13,
    "Anomalies Detected": 6
  },
  {
    "_id": "698ec0002d2b92cf4e8efc99",
    "Month": "2025-11",
    "State": "Delhi",
    "RTO": "DEL-RTO-2",
    "Staff - Total": 136,
    "Staff - Counter": 51,
    "Staff - Field Enforcement": 30,
    "Staff - Back Office": 37,
    "Staff - Call Center": 18,
    "Anomalies Detected": 2
  },
  {
    "_id": "698ec0002d2b92cf4e8efc9a",
    "Month": "2025-12",
    "State": "Delhi",
    "RTO": "DEL-RTO-2",
    "Staff - Total": 139,
    "Staff - Counter": 43,
    "Staff - Field Enforcement": 38,
    "Staff - Back Office": 36,
    "Staff - Call Center": 22,
    "Anomalies Detected": 11
  },
  {
    "_id": "698ec0002d2b92cf4e8efc9b",
    "Month": "2026-01",
    "State": "Delhi",
    "RTO": "DEL-RTO-2",
    "Staff - Total": 218,
    "Staff - Counter": 82,
    "Staff - Field Enforcement": 52,
    "Staff - Back Office": 64,
    "Staff - Call Center": 20,
    "Anomalies Detected": 6
  },
  {
    "_id": "698ec0002d2b92cf4e8efc9c",
    "Month": "2025-04",
    "State": "Delhi",
    "RTO": "DEL-RTO-3",
    "Staff - Total": 71,
    "Staff - Counter": 29,
    "Staff - Field Enforcement": 21,
    "Staff - Back Office": 24,
    "Staff - Call Center": 3,
    "Anomalies Detected": 1
  },
  {
    "_id": "698ec0002d2b92cf4e8efc9d",
    "Month": "2025-05",
    "State": "Delhi",
    "RTO": "DEL-RTO-3",
    "Staff - Total": 158,
    "Staff - Counter": 55,
    "Staff - Field Enforcement": 37,
    "Staff - Back Office": 43,
    "Staff - Call Center": 23,
    "Anomalies Detected": 4
  },
  {
    "_id": "698ec0002d2b92cf4e8efc9e",
    "Month": "2025-06",
    "State": "Delhi",
    "RTO": "DEL-RTO-3",
    "Staff - Total": 155,
    "Staff - Counter": 58,
    "Staff - Field Enforcement": 35,
    "Staff - Back Office": 46,
    "Staff - Call Center": 16,
    "Anomalies Detected": 1
  },
  {
    "_id": "698ec0002d2b92cf4e8efc9f",
    "Month": "2025-07",
    "State": "Delhi",
    "RTO": "DEL-RTO-3",
    "Staff - Total": 146,
    "Staff - Counter": 45,
    "Staff - Field Enforcement": 37,
    "Staff - Back Office": 41,
    "Staff - Call Center": 23,
    "Anomalies Detected": 0
  },
  {
    "_id": "698ec0002d2b92cf4e8efca0",
    "Month": "2025-08",
    "State": "Delhi",
    "RTO": "DEL-RTO-3",
    "Staff - Total": 84,
    "Staff - Counter": 22,
    "Staff - Field Enforcement": 14,
    "Staff - Back Office": 23,
    "Staff - Call Center": 25,
    "Anomalies Detected": 2
  },
  {
    "_id": "698ec0002d2b92cf4e8efca1",
    "Month": "2025-09",
    "State": "Delhi",
    "RTO": "DEL-RTO-3",
    "Staff - Total": 142,
    "Staff - Counter": 45,
    "Staff - Field Enforcement": 38,
    "Staff - Back Office": 42,
    "Staff - Call Center": 17,
    "Anomalies Detected": 5
  },
  {
    "_id": "698ec0002d2b92cf4e8efca2",
    "Month": "2025-10",
    "State": "Delhi",
    "RTO": "DEL-RTO-3",
    "Staff - Total": 90,
    "Staff - Counter": 30,
    "Staff - Field Enforcement": 19,
    "Staff - Back Office": 27,
    "Staff - Call Center": 14,
    "Anomalies Detected": 4
  },
  {
    "_id": "698ec0002d2b92cf4e8efca3",
    "Month": "2025-11",
    "State": "Delhi",
    "RTO": "DEL-RTO-3",
    "Staff - Total": 63,
    "Staff - Counter": 24,
    "Staff - Field Enforcement": 12,
    "Staff - Back Office": 23,
    "Staff - Call Center": 4,
    "Anomalies Detected": 12
  },
  {
    "_id": "698ec0002d2b92cf4e8efca4",
    "Month": "2025-12",
    "State": "Delhi",
    "RTO": "DEL-RTO-3",
    "Staff - Total": 206,
    "Staff - Counter": 77,
    "Staff - Field Enforcement": 47,
    "Staff - Back Office": 58,
    "Staff - Call Center": 24,
    "Anomalies Detected": 9
  },
  {
    "_id": "698ec0002d2b92cf4e8efca5",
    "Month": "2026-01",
    "State": "Delhi",
    "RTO": "DEL-RTO-3",
    "Staff - Total": 172,
    "Staff - Counter": 66,
    "Staff - Field Enforcement": 49,
    "Staff - Back Office": 51,
    "Staff - Call Center": 6,
    "Anomalies Detected": 8
  },
  {
    "_id": "698ec0002d2b92cf4e8efca6",
    "Month": "2025-04",
    "State": "Karnataka",
    "RTO": "KAR-RTO-1",
    "Staff - Total": 187,
    "Staff - Counter": 64,
    "Staff - Field Enforcement": 51,
    "Staff - Back Office": 51,
    "Staff - Call Center": 21,
    "Anomalies Detected": 5
  },
  {
    "_id": "698ec0002d2b92cf4e8efca7",
    "Month": "2025-05",
    "State": "Karnataka",
    "RTO": "KAR-RTO-1",
    "Staff - Total": 83,
    "Staff - Counter": 17,
    "Staff - Field Enforcement": 16,
    "Staff - Back Office": 27,
    "Staff - Call Center": 23,
    "Anomalies Detected": 3
  },
  {
    "_id": "698ec0002d2b92cf4e8efca8",
    "Month": "2025-06",
    "State": "Karnataka",
    "RTO": "KAR-RTO-1",
    "Staff - Total": 185,
    "Staff - Counter": 66,
    "Staff - Field Enforcement": 49,
    "Staff - Back Office": 52,
    "Staff - Call Center": 18,
    "Anomalies Detected": 12
  },
  {
    "_id": "698ec0002d2b92cf4e8efca9",
    "Month": "2025-07",
    "State": "Karnataka",
    "RTO": "KAR-RTO-1",
    "Staff - Total": 228,
    "Staff - Counter": 77,
    "Staff - Field Enforcement": 53,
    "Staff - Back Office": 67,
    "Staff - Call Center": 31,
    "Anomalies Detected": 10
  },
  {
    "_id": "698ec0002d2b92cf4e8efcaa",
    "Month": "2025-08",
    "State": "Karnataka",
    "RTO": "KAR-RTO-1",
    "Staff - Total": 219,
    "Staff - Counter": 75,
    "Staff - Field Enforcement": 61,
    "Staff - Back Office": 62,
    "Staff - Call Center": 21,
    "Anomalies Detected": 0
  },
  {
    "_id": "698ec0002d2b92cf4e8efcab",
    "Month": "2025-09",
    "State": "Karnataka",
    "RTO": "KAR-RTO-1",
    "Staff - Total": 77,
    "Staff - Counter": 21,
    "Staff - Field Enforcement": 19,
    "Staff - Back Office": 29,
    "Staff - Call Center": 8,
    "Anomalies Detected": 2
  },
  {
    "_id": "698ec0002d2b92cf4e8efcac",
    "Month": "2025-10",
    "State": "Karnataka",
    "RTO": "KAR-RTO-1",
    "Staff - Total": 214,
    "Staff - Counter": 72,
    "Staff - Field Enforcement": 55,
    "Staff - Back Office": 66,
    "Staff - Call Center": 21,
    "Anomalies Detected": 9
  },
  {
    "_id": "698ec0002d2b92cf4e8efcad",
    "Month": "2025-11",
    "State": "Karnataka",
    "RTO": "KAR-RTO-1",
    "Staff - Total": 197,
    "Staff - Counter": 72,
    "Staff - Field Enforcement": 56,
    "Staff - Back Office": 61,
    "Staff - Call Center": 8,
    "Anomalies Detected": 8
  },
  {
    "_id": "698ec0002d2b92cf4e8efcae",
    "Month": "2025-12",
    "State": "Karnataka",
    "RTO": "KAR-RTO-1",
    "Staff - Total": 108,
    "Staff - Counter": 41,
    "Staff - Field Enforcement": 21,
    "Staff - Back Office": 34,
    "Staff - Call Center": 12,
    "Anomalies Detected": 5
  },
  {
    "_id": "698ec0002d2b92cf4e8efcaf",
    "Month": "2026-01",
    "State": "Karnataka",
    "RTO": "KAR-RTO-1",
    "Staff - Total": 151,
    "Staff - Counter": 49,
    "Staff - Field Enforcement": 46,
    "Staff - Back Office": 44,
    "Staff - Call Center": 12,
    "Anomalies Detected": 9
  },
  {
    "_id": "698ec0002d2b92cf4e8efcb0",
    "Month": "2025-04",
    "State": "Karnataka",
    "RTO": "KAR-RTO-2",
    "Staff - Total": 158,
    "Staff - Counter": 61,
    "Staff - Field Enforcement": 35,
    "Staff - Back Office": 45,
    "Staff - Call Center": 17,
    "Anomalies Detected": 6
  },
  {
    "_id": "698ec0002d2b92cf4e8efcb1",
    "Month": "2025-05",
    "State": "Karnataka",
    "RTO": "KAR-RTO-2",
    "Staff - Total": 163,
    "Staff - Counter": 57,
    "Staff - Field Enforcement": 34,
    "Staff - Back Office": 51,
    "Staff - Call Center": 21,
    "Anomalies Detected": 12
  },
  {
    "_id": "698ec0002d2b92cf4e8efcb2",
    "Month": "2025-06",
    "State": "Karnataka",
    "RTO": "KAR-RTO-2",
    "Staff - Total": 229,
    "Staff - Counter": 87,
    "Staff - Field Enforcement": 54,
    "Staff - Back Office": 73,
    "Staff - Call Center": 15,
    "Anomalies Detected": 10
  },
  {
    "_id": "698ec0002d2b92cf4e8efcb3",
    "Month": "2025-07",
    "State": "Karnataka",
    "RTO": "KAR-RTO-2",
    "Staff - Total": 125,
    "Staff - Counter": 39,
    "Staff - Field Enforcement": 30,
    "Staff - Back Office": 39,
    "Staff - Call Center": 17,
    "Anomalies Detected": 4
  },
  {
    "_id": "698ec0002d2b92cf4e8efcb4",
    "Month": "2025-08",
    "State": "Karnataka",
    "RTO": "KAR-RTO-2",
    "Staff - Total": 67,
    "Staff - Counter": 24,
    "Staff - Field Enforcement": 15,
    "Staff - Back Office": 18,
    "Staff - Call Center": 10,
    "Anomalies Detected": 6
  },
  {
    "_id": "698ec0002d2b92cf4e8efcb5",
    "Month": "2025-09",
    "State": "Karnataka",
    "RTO": "KAR-RTO-2",
    "Staff - Total": 155,
    "Staff - Counter": 54,
    "Staff - Field Enforcement": 39,
    "Staff - Back Office": 43,
    "Staff - Call Center": 19,
    "Anomalies Detected": 6
  },
  {
    "_id": "698ec0002d2b92cf4e8efcb6",
    "Month": "2025-10",
    "State": "Karnataka",
    "RTO": "KAR-RTO-2",
    "Staff - Total": 70,
    "Staff - Counter": 23,
    "Staff - Field Enforcement": 17,
    "Staff - Back Office": 18,
    "Staff - Call Center": 12,
    "Anomalies Detected": 10
  },
  {
    "_id": "698ec0002d2b92cf4e8efcb7",
    "Month": "2025-11",
    "State": "Karnataka",
    "RTO": "KAR-RTO-2",
    "Staff - Total": 82,
    "Staff - Counter": 19,
    "Staff - Field Enforcement": 17,
    "Staff - Back Office": 23,
    "Staff - Call Center": 23,
    "Anomalies Detected": 0
  },
  {
    "_id": "698ec0002d2b92cf4e8efcb8",
    "Month": "2025-12",
    "State": "Karnataka",
    "RTO": "KAR-RTO-2",
    "Staff - Total": 181,
    "Staff - Counter": 71,
    "Staff - Field Enforcement": 45,
    "Staff - Back Office": 55,
    "Staff - Call Center": 10,
    "Anomalies Detected": 9
  },
  {
    "_id": "698ec0002d2b92cf4e8efcb9",
    "Month": "2026-01",
    "State": "Karnataka",
    "RTO": "KAR-RTO-2",
    "Staff - Total": 145,
    "Staff - Counter": 50,
    "Staff - Field Enforcement": 31,
    "Staff - Back Office": 42,
    "Staff - Call Center": 22,
    "Anomalies Detected": 0
  },
  {
    "_id": "698ec0002d2b92cf4e8efcba",
    "Month": "2025-04",
    "State": "Karnataka",
    "RTO": "KAR-RTO-3",
    "Staff - Total": 126,
    "Staff - Counter": 42,
    "Staff - Field Enforcement": 21,
    "Staff - Back Office": 32,
    "Staff - Call Center": 31,
    "Anomalies Detected": 5
  },
  {
    "_id": "698ec0002d2b92cf4e8efcbb",
    "Month": "2025-05",
    "State": "Karnataka",
    "RTO": "KAR-RTO-3",
    "Staff - Total": 182,
    "Staff - Counter": 67,
    "Staff - Field Enforcement": 50,
    "Staff - Back Office": 61,
    "Staff - Call Center": 4,
    "Anomalies Detected": 11
  },
  {
    "_id": "698ec0002d2b92cf4e8efcbc",
    "Month": "2025-06",
    "State": "Karnataka",
    "RTO": "KAR-RTO-3",
    "Staff - Total": 186,
    "Staff - Counter": 62,
    "Staff - Field Enforcement": 42,
    "Staff - Back Office": 61,
    "Staff - Call Center": 21,
    "Anomalies Detected": 7
  },
  {
    "_id": "698ec0002d2b92cf4e8efcbd",
    "Month": "2025-07",
    "State": "Karnataka",
    "RTO": "KAR-RTO-3",
    "Staff - Total": 201,
    "Staff - Counter": 82,
    "Staff - Field Enforcement": 48,
    "Staff - Back Office": 70,
    "Staff - Call Center": 3,
    "Anomalies Detected": 6
  },
  {
    "_id": "698ec0002d2b92cf4e8efcbe",
    "Month": "2025-08",
    "State": "Karnataka",
    "RTO": "KAR-RTO-3",
    "Staff - Total": 172,
    "Staff - Counter": 66,
    "Staff - Field Enforcement": 49,
    "Staff - Back Office": 46,
    "Staff - Call Center": 11,
    "Anomalies Detected": 0
  },
  {
    "_id": "698ec0002d2b92cf4e8efcbf",
    "Month": "2025-09",
    "State": "Karnataka",
    "RTO": "KAR-RTO-3",
    "Staff - Total": 229,
    "Staff - Counter": 74,
    "Staff - Field Enforcement": 52,
    "Staff - Back Office": 72,
    "Staff - Call Center": 31,
    "Anomalies Detected": 2
  },
  {
    "_id": "698ec0002d2b92cf4e8efcc0",
    "Month": "2025-10",
    "State": "Karnataka",
    "RTO": "KAR-RTO-3",
    "Staff - Total": 184,
    "Staff - Counter": 64,
    "Staff - Field Enforcement": 48,
    "Staff - Back Office": 45,
    "Staff - Call Center": 27,
    "Anomalies Detected": 10
  },
  {
    "_id": "698ec0002d2b92cf4e8efcc1",
    "Month": "2025-11",
    "State": "Karnataka",
    "RTO": "KAR-RTO-3",
    "Staff - Total": 198,
    "Staff - Counter": 67,
    "Staff - Field Enforcement": 51,
    "Staff - Back Office": 62,
    "Staff - Call Center": 18,
    "Anomalies Detected": 1
  },
  {
    "_id": "698ec0002d2b92cf4e8efcc2",
    "Month": "2025-12",
    "State": "Karnataka",
    "RTO": "KAR-RTO-3",
    "Staff - Total": 192,
    "Staff - Counter": 66,
    "Staff - Field Enforcement": 39,
    "Staff - Back Office": 57,
    "Staff - Call Center": 30,
    "Anomalies Detected": 12
  },
  {
    "_id": "698ec0002d2b92cf4e8efcc3",
    "Month": "2026-01",
    "State": "Karnataka",
    "RTO": "KAR-RTO-3",
    "Staff - Total": 96,
    "Staff - Counter": 28,
    "Staff - Field Enforcement": 24,
    "Staff - Back Office": 26,
    "Staff - Call Center": 18,
    "Anomalies Detected": 3
  },
  {
    "_id": "698ec0002d2b92cf4e8efcc4",
    "Month": "2025-04",
    "State": "Tamil Nadu",
    "RTO": "TAM-RTO-1",
    "Staff - Total": 105,
    "Staff - Counter": 40,
    "Staff - Field Enforcement": 23,
    "Staff - Back Office": 29,
    "Staff - Call Center": 13,
    "Anomalies Detected": 12
  },
  {
    "_id": "698ec0002d2b92cf4e8efcc5",
    "Month": "2025-05",
    "State": "Tamil Nadu",
    "RTO": "TAM-RTO-1",
    "Staff - Total": 109,
    "Staff - Counter": 44,
    "Staff - Field Enforcement": 27,
    "Staff - Back Office": 33,
    "Staff - Call Center": 5,
    "Anomalies Detected": 0
  },
  {
    "_id": "698ec0002d2b92cf4e8efcc6",
    "Month": "2025-06",
    "State": "Tamil Nadu",
    "RTO": "TAM-RTO-1",
    "Staff - Total": 162,
    "Staff - Counter": 59,
    "Staff - Field Enforcement": 45,
    "Staff - Back Office": 51,
    "Staff - Call Center": 7,
    "Anomalies Detected": 8
  },
  {
    "_id": "698ec0002d2b92cf4e8efcc7",
    "Month": "2025-07",
    "State": "Tamil Nadu",
    "RTO": "TAM-RTO-1",
    "Staff - Total": 218,
    "Staff - Counter": 79,
    "Staff - Field Enforcement": 48,
    "Staff - Back Office": 61,
    "Staff - Call Center": 30,
    "Anomalies Detected": 11
  },
  {
    "_id": "698ec0002d2b92cf4e8efcc8",
    "Month": "2025-08",
    "State": "Tamil Nadu",
    "RTO": "TAM-RTO-1",
    "Staff - Total": 106,
    "Staff - Counter": 33,
    "Staff - Field Enforcement": 22,
    "Staff - Back Office": 22,
    "Staff - Call Center": 29,
    "Anomalies Detected": 11
  },
  {
    "_id": "698ec0002d2b92cf4e8efcc9",
    "Month": "2025-09",
    "State": "Tamil Nadu",
    "RTO": "TAM-RTO-1",
    "Staff - Total": 69,
    "Staff - Counter": 22,
    "Staff - Field Enforcement": 16,
    "Staff - Back Office": 16,
    "Staff - Call Center": 15,
    "Anomalies Detected": 5
  },
  {
    "_id": "698ec0002d2b92cf4e8efcca",
    "Month": "2025-10",
    "State": "Tamil Nadu",
    "RTO": "TAM-RTO-1",
    "Staff - Total": 179,
    "Staff - Counter": 60,
    "Staff - Field Enforcement": 49,
    "Staff - Back Office": 52,
    "Staff - Call Center": 18,
    "Anomalies Detected": 8
  },
  {
    "_id": "698ec0002d2b92cf4e8efccb",
    "Month": "2025-11",
    "State": "Tamil Nadu",
    "RTO": "TAM-RTO-1",
    "Staff - Total": 83,
    "Staff - Counter": 30,
    "Staff - Field Enforcement": 15,
    "Staff - Back Office": 24,
    "Staff - Call Center": 14,
    "Anomalies Detected": 12
  },
  {
    "_id": "698ec0002d2b92cf4e8efccc",
    "Month": "2025-12",
    "State": "Tamil Nadu",
    "RTO": "TAM-RTO-1",
    "Staff - Total": 227,
    "Staff - Counter": 78,
    "Staff - Field Enforcement": 53,
    "Staff - Back Office": 70,
    "Staff - Call Center": 26,
    "Anomalies Detected": 12
  },
  {
    "_id": "698ec0002d2b92cf4e8efccd",
    "Month": "2026-01",
    "State": "Tamil Nadu",
    "RTO": "TAM-RTO-1",
    "Staff - Total": 207,
    "Staff - Counter": 72,
    "Staff - Field Enforcement": 54,
    "Staff - Back Office": 66,
    "Staff - Call Center": 15,
    "Anomalies Detected": 4
  },
  {
    "_id": "698ec0002d2b92cf4e8efcce",
    "Month": "2025-04",
    "State": "Tamil Nadu",
    "RTO": "TAM-RTO-2",
    "Staff - Total": 134,
    "Staff - Counter": 46,
    "Staff - Field Enforcement": 34,
    "Staff - Back Office": 47,
    "Staff - Call Center": 7,
    "Anomalies Detected": 7
  },
  {
    "_id": "698ec0002d2b92cf4e8efccf",
    "Month": "2025-05",
    "State": "Tamil Nadu",
    "RTO": "TAM-RTO-2",
    "Staff - Total": 193,
    "Staff - Counter": 62,
    "Staff - Field Enforcement": 59,
    "Staff - Back Office": 56,
    "Staff - Call Center": 16,
    "Anomalies Detected": 8
  },
  {
    "_id": "698ec0002d2b92cf4e8efcd0",
    "Month": "2025-06",
    "State": "Tamil Nadu",
    "RTO": "TAM-RTO-2",
    "Staff - Total": 226,
    "Staff - Counter": 76,
    "Staff - Field Enforcement": 45,
    "Staff - Back Office": 69,
    "Staff - Call Center": 36,
    "Anomalies Detected": 10
  },
  {
    "_id": "698ec0002d2b92cf4e8efcd1",
    "Month": "2025-07",
    "State": "Tamil Nadu",
    "RTO": "TAM-RTO-2",
    "Staff - Total": 180,
    "Staff - Counter": 58,
    "Staff - Field Enforcement": 43,
    "Staff - Back Office": 58,
    "Staff - Call Center": 21,
    "Anomalies Detected": 3
  },
  {
    "_id": "698ec0002d2b92cf4e8efcd2",
    "Month": "2025-08",
    "State": "Tamil Nadu",
    "RTO": "TAM-RTO-2",
    "Staff - Total": 66,
    "Staff - Counter": 16,
    "Staff - Field Enforcement": 15,
    "Staff - Back Office": 16,
    "Staff - Call Center": 19,
    "Anomalies Detected": 12
  },
  {
    "_id": "698ec0002d2b92cf4e8efcd3",
    "Month": "2025-09",
    "State": "Tamil Nadu",
    "RTO": "TAM-RTO-2",
    "Staff - Total": 138,
    "Staff - Counter": 41,
    "Staff - Field Enforcement": 35,
    "Staff - Back Office": 40,
    "Staff - Call Center": 22,
    "Anomalies Detected": 11
  },
  {
    "_id": "698ec0002d2b92cf4e8efcd4",
    "Month": "2025-10",
    "State": "Tamil Nadu",
    "RTO": "TAM-RTO-2",
    "Staff - Total": 131,
    "Staff - Counter": 46,
    "Staff - Field Enforcement": 33,
    "Staff - Back Office": 32,
    "Staff - Call Center": 20,
    "Anomalies Detected": 4
  },
  {
    "_id": "698ec0002d2b92cf4e8efcd5",
    "Month": "2025-11",
    "State": "Tamil Nadu",
    "RTO": "TAM-RTO-2",
    "Staff - Total": 77,
    "Staff - Counter": 25,
    "Staff - Field Enforcement": 18,
    "Staff - Back Office": 28,
    "Staff - Call Center": 6,
    "Anomalies Detected": 8
  },
  {
    "_id": "698ec0002d2b92cf4e8efcd6",
    "Month": "2025-12",
    "State": "Tamil Nadu",
    "RTO": "TAM-RTO-2",
    "Staff - Total": 121,
    "Staff - Counter": 49,
    "Staff - Field Enforcement": 36,
    "Staff - Back Office": 40,
    "Staff - Call Center": 3,
    "Anomalies Detected": 3
  },
  {
    "_id": "698ec0002d2b92cf4e8efcd7",
    "Month": "2026-01",
    "State": "Tamil Nadu",
    "RTO": "TAM-RTO-2",
    "Staff - Total": 159,
    "Staff - Counter": 44,
    "Staff - Field Enforcement": 44,
    "Staff - Back Office": 48,
    "Staff - Call Center": 23,
    "Anomalies Detected": 4
  },
  {
    "_id": "698ec0002d2b92cf4e8efcd8",
    "Month": "2025-04",
    "State": "Tamil Nadu",
    "RTO": "TAM-RTO-3",
    "Staff - Total": 238,
    "Staff - Counter": 89,
    "Staff - Field Enforcement": 56,
    "Staff - Back Office": 69,
    "Staff - Call Center": 24,
    "Anomalies Detected": 5
  },
  {
    "_id": "698ec0002d2b92cf4e8efcd9",
    "Month": "2025-05",
    "State": "Tamil Nadu",
    "RTO": "TAM-RTO-3",
    "Staff - Total": 233,
    "Staff - Counter": 75,
    "Staff - Field Enforcement": 57,
    "Staff - Back Office": 75,
    "Staff - Call Center": 26,
    "Anomalies Detected": 0
  },
  {
    "_id": "698ec0002d2b92cf4e8efcda",
    "Month": "2025-06",
    "State": "Tamil Nadu",
    "RTO": "TAM-RTO-3",
    "Staff - Total": 229,
    "Staff - Counter": 86,
    "Staff - Field Enforcement": 61,
    "Staff - Back Office": 68,
    "Staff - Call Center": 14,
    "Anomalies Detected": 11
  },
  {
    "_id": "698ec0002d2b92cf4e8efcdb",
    "Month": "2025-07",
    "State": "Tamil Nadu",
    "RTO": "TAM-RTO-3",
    "Staff - Total": 186,
    "Staff - Counter": 59,
    "Staff - Field Enforcement": 49,
    "Staff - Back Office": 48,
    "Staff - Call Center": 30,
    "Anomalies Detected": 6
  },
  {
    "_id": "698ec0002d2b92cf4e8efcdc",
    "Month": "2025-08",
    "State": "Tamil Nadu",
    "RTO": "TAM-RTO-3",
    "Staff - Total": 76,
    "Staff - Counter": 28,
    "Staff - Field Enforcement": 24,
    "Staff - Back Office": 19,
    "Staff - Call Center": 5,
    "Anomalies Detected": 0
  },
  {
    "_id": "698ec0002d2b92cf4e8efcdd",
    "Month": "2025-09",
    "State": "Tamil Nadu",
    "RTO": "TAM-RTO-3",
    "Staff - Total": 193,
    "Staff - Counter": 67,
    "Staff - Field Enforcement": 49,
    "Staff - Back Office": 57,
    "Staff - Call Center": 20,
    "Anomalies Detected": 9
  },
  {
    "_id": "698ec0002d2b92cf4e8efcde",
    "Month": "2025-10",
    "State": "Tamil Nadu",
    "RTO": "TAM-RTO-3",
    "Staff - Total": 237,
    "Staff - Counter": 78,
    "Staff - Field Enforcement": 59,
    "Staff - Back Office": 73,
    "Staff - Call Center": 27,
    "Anomalies Detected": 4
  },
  {
    "_id": "698ec0002d2b92cf4e8efcdf",
    "Month": "2025-11",
    "State": "Tamil Nadu",
    "RTO": "TAM-RTO-3",
    "Staff - Total": 236,
    "Staff - Counter": 86,
    "Staff - Field Enforcement": 59,
    "Staff - Back Office": 74,
    "Staff - Call Center": 17,
    "Anomalies Detected": 0
  },
  {
    "_id": "698ec0002d2b92cf4e8efce0",
    "Month": "2025-12",
    "State": "Tamil Nadu",
    "RTO": "TAM-RTO-3",
    "Staff - Total": 239,
    "Staff - Counter": 85,
    "Staff - Field Enforcement": 57,
    "Staff - Back Office": 68,
    "Staff - Call Center": 29,
    "Anomalies Detected": 10
  },
  {
    "_id": "698ec0002d2b92cf4e8efce1",
    "Month": "2026-01",
    "State": "Tamil Nadu",
    "RTO": "TAM-RTO-3",
    "Staff - Total": 90,
    "Staff - Counter": 34,
    "Staff - Field Enforcement": 18,
    "Staff - Back Office": 27,
    "Staff - Call Center": 11,
    "Anomalies Detected": 12
  },
  {
    "_id": "698ec0002d2b92cf4e8efce2",
    "Month": "2025-04",
    "State": "Uttar Pradesh",
    "RTO": "UTT-RTO-1",
    "Staff - Total": 169,
    "Staff - Counter": 56,
    "Staff - Field Enforcement": 46,
    "Staff - Back Office": 50,
    "Staff - Call Center": 17,
    "Anomalies Detected": 5
  },
  {
    "_id": "698ec0002d2b92cf4e8efce3",
    "Month": "2025-05",
    "State": "Uttar Pradesh",
    "RTO": "UTT-RTO-1",
    "Staff - Total": 175,
    "Staff - Counter": 46,
    "Staff - Field Enforcement": 42,
    "Staff - Back Office": 54,
    "Staff - Call Center": 33,
    "Anomalies Detected": 6
  },
  {
    "_id": "698ec0002d2b92cf4e8efce4",
    "Month": "2025-06",
    "State": "Uttar Pradesh",
    "RTO": "UTT-RTO-1",
    "Staff - Total": 170,
    "Staff - Counter": 64,
    "Staff - Field Enforcement": 41,
    "Staff - Back Office": 50,
    "Staff - Call Center": 15,
    "Anomalies Detected": 5
  },
  {
    "_id": "698ec0002d2b92cf4e8efce5",
    "Month": "2025-07",
    "State": "Uttar Pradesh",
    "RTO": "UTT-RTO-1",
    "Staff - Total": 161,
    "Staff - Counter": 55,
    "Staff - Field Enforcement": 35,
    "Staff - Back Office": 39,
    "Staff - Call Center": 32,
    "Anomalies Detected": 12
  },
  {
    "_id": "698ec0002d2b92cf4e8efce6",
    "Month": "2025-08",
    "State": "Uttar Pradesh",
    "RTO": "UTT-RTO-1",
    "Staff - Total": 179,
    "Staff - Counter": 70,
    "Staff - Field Enforcement": 43,
    "Staff - Back Office": 54,
    "Staff - Call Center": 12,
    "Anomalies Detected": 8
  },
  {
    "_id": "698ec0002d2b92cf4e8efce7",
    "Month": "2025-09",
    "State": "Uttar Pradesh",
    "RTO": "UTT-RTO-1",
    "Staff - Total": 185,
    "Staff - Counter": 55,
    "Staff - Field Enforcement": 49,
    "Staff - Back Office": 44,
    "Staff - Call Center": 37,
    "Anomalies Detected": 10
  },
  {
    "_id": "698ec0002d2b92cf4e8efce8",
    "Month": "2025-10",
    "State": "Uttar Pradesh",
    "RTO": "UTT-RTO-1",
    "Staff - Total": 133,
    "Staff - Counter": 46,
    "Staff - Field Enforcement": 34,
    "Staff - Back Office": 36,
    "Staff - Call Center": 17,
    "Anomalies Detected": 4
  },
  {
    "_id": "698ec0002d2b92cf4e8efce9",
    "Month": "2025-11",
    "State": "Uttar Pradesh",
    "RTO": "UTT-RTO-1",
    "Staff - Total": 131,
    "Staff - Counter": 41,
    "Staff - Field Enforcement": 29,
    "Staff - Back Office": 35,
    "Staff - Call Center": 26,
    "Anomalies Detected": 3
  },
  {
    "_id": "698ec0002d2b92cf4e8efcea",
    "Month": "2025-12",
    "State": "Uttar Pradesh",
    "RTO": "UTT-RTO-1",
    "Staff - Total": 98,
    "Staff - Counter": 28,
    "Staff - Field Enforcement": 25,
    "Staff - Back Office": 30,
    "Staff - Call Center": 15,
    "Anomalies Detected": 1
  },
  {
    "_id": "698ec0002d2b92cf4e8efceb",
    "Month": "2026-01",
    "State": "Uttar Pradesh",
    "RTO": "UTT-RTO-1",
    "Staff - Total": 239,
    "Staff - Counter": 82,
    "Staff - Field Enforcement": 62,
    "Staff - Back Office": 70,
    "Staff - Call Center": 25,
    "Anomalies Detected": 7
  },
  {
    "_id": "698ec0002d2b92cf4e8efcec",
    "Month": "2025-04",
    "State": "Uttar Pradesh",
    "RTO": "UTT-RTO-2",
    "Staff - Total": 95,
    "Staff - Counter": 25,
    "Staff - Field Enforcement": 13,
    "Staff - Back Office": 30,
    "Staff - Call Center": 27,
    "Anomalies Detected": 2
  },
  {
    "_id": "698ec0002d2b92cf4e8efced",
    "Month": "2025-05",
    "State": "Uttar Pradesh",
    "RTO": "UTT-RTO-2",
    "Staff - Total": 61,
    "Staff - Counter": 23,
    "Staff - Field Enforcement": 13,
    "Staff - Back Office": 25,
    "Staff - Call Center": 3,
    "Anomalies Detected": 5
  },
  {
    "_id": "698ec0002d2b92cf4e8efcee",
    "Month": "2025-06",
    "State": "Uttar Pradesh",
    "RTO": "UTT-RTO-2",
    "Staff - Total": 98,
    "Staff - Counter": 36,
    "Staff - Field Enforcement": 26,
    "Staff - Back Office": 37,
    "Staff - Call Center": 3,
    "Anomalies Detected": 3
  },
  {
    "_id": "698ec0002d2b92cf4e8efcef",
    "Month": "2025-07",
    "State": "Uttar Pradesh",
    "RTO": "UTT-RTO-2",
    "Staff - Total": 196,
    "Staff - Counter": 65,
    "Staff - Field Enforcement": 43,
    "Staff - Back Office": 66,
    "Staff - Call Center": 22,
    "Anomalies Detected": 9
  },
  {
    "_id": "698ec0002d2b92cf4e8efcf0",
    "Month": "2025-08",
    "State": "Uttar Pradesh",
    "RTO": "UTT-RTO-2",
    "Staff - Total": 106,
    "Staff - Counter": 39,
    "Staff - Field Enforcement": 38,
    "Staff - Back Office": 33,
    "Staff - Call Center": 3,
    "Anomalies Detected": 0
  },
  {
    "_id": "698ec0002d2b92cf4e8efcf1",
    "Month": "2025-09",
    "State": "Uttar Pradesh",
    "RTO": "UTT-RTO-2",
    "Staff - Total": 223,
    "Staff - Counter": 77,
    "Staff - Field Enforcement": 51,
    "Staff - Back Office": 64,
    "Staff - Call Center": 31,
    "Anomalies Detected": 1
  },
  {
    "_id": "698ec0002d2b92cf4e8efcf2",
    "Month": "2025-10",
    "State": "Uttar Pradesh",
    "RTO": "UTT-RTO-2",
    "Staff - Total": 201,
    "Staff - Counter": 67,
    "Staff - Field Enforcement": 44,
    "Staff - Back Office": 68,
    "Staff - Call Center": 22,
    "Anomalies Detected": 8
  },
  {
    "_id": "698ec0002d2b92cf4e8efcf3",
    "Month": "2025-11",
    "State": "Uttar Pradesh",
    "RTO": "UTT-RTO-2",
    "Staff - Total": 72,
    "Staff - Counter": 24,
    "Staff - Field Enforcement": 21,
    "Staff - Back Office": 23,
    "Staff - Call Center": 4,
    "Anomalies Detected": 10
  },
  {
    "_id": "698ec0002d2b92cf4e8efcf4",
    "Month": "2025-12",
    "State": "Uttar Pradesh",
    "RTO": "UTT-RTO-2",
    "Staff - Total": 106,
    "Staff - Counter": 40,
    "Staff - Field Enforcement": 27,
    "Staff - Back Office": 35,
    "Staff - Call Center": 4,
    "Anomalies Detected": 1
  },
  {
    "_id": "698ec0002d2b92cf4e8efcf5",
    "Month": "2026-01",
    "State": "Uttar Pradesh",
    "RTO": "UTT-RTO-2",
    "Staff - Total": 166,
    "Staff - Counter": 58,
    "Staff - Field Enforcement": 40,
    "Staff - Back Office": 57,
    "Staff - Call Center": 11,
    "Anomalies Detected": 10
  },
  {
    "_id": "698ec0002d2b92cf4e8efcf6",
    "Month": "2025-04",
    "State": "Uttar Pradesh",
    "RTO": "UTT-RTO-3",
    "Staff - Total": 60,
    "Staff - Counter": 22,
    "Staff - Field Enforcement": 16,
    "Staff - Back Office": 14,
    "Staff - Call Center": 8,
    "Anomalies Detected": 7
  },
  {
    "_id": "698ec0002d2b92cf4e8efcf7",
    "Month": "2025-05",
    "State": "Uttar Pradesh",
    "RTO": "UTT-RTO-3",
    "Staff - Total": 140,
    "Staff - Counter": 47,
    "Staff - Field Enforcement": 33,
    "Staff - Back Office": 34,
    "Staff - Call Center": 26,
    "Anomalies Detected": 11
  },
  {
    "_id": "698ec0002d2b92cf4e8efcf8",
    "Month": "2025-06",
    "State": "Uttar Pradesh",
    "RTO": "UTT-RTO-3",
    "Staff - Total": 226,
    "Staff - Counter": 80,
    "Staff - Field Enforcement": 61,
    "Staff - Back Office": 70,
    "Staff - Call Center": 15,
    "Anomalies Detected": 5
  },
  {
    "_id": "698ec0002d2b92cf4e8efcf9",
    "Month": "2025-07",
    "State": "Uttar Pradesh",
    "RTO": "UTT-RTO-3",
    "Staff - Total": 112,
    "Staff - Counter": 42,
    "Staff - Field Enforcement": 25,
    "Staff - Back Office": 35,
    "Staff - Call Center": 10,
    "Anomalies Detected": 4
  },
  {
    "_id": "698ec0002d2b92cf4e8efcfa",
    "Month": "2025-08",
    "State": "Uttar Pradesh",
    "RTO": "UTT-RTO-3",
    "Staff - Total": 195,
    "Staff - Counter": 67,
    "Staff - Field Enforcement": 48,
    "Staff - Back Office": 58,
    "Staff - Call Center": 22,
    "Anomalies Detected": 3
  },
  {
    "_id": "698ec0002d2b92cf4e8efcfb",
    "Month": "2025-09",
    "State": "Uttar Pradesh",
    "RTO": "UTT-RTO-3",
    "Staff - Total": 211,
    "Staff - Counter": 73,
    "Staff - Field Enforcement": 57,
    "Staff - Back Office": 67,
    "Staff - Call Center": 14,
    "Anomalies Detected": 9
  },
  {
    "_id": "698ec0002d2b92cf4e8efcfc",
    "Month": "2025-10",
    "State": "Uttar Pradesh",
    "RTO": "UTT-RTO-3",
    "Staff - Total": 139,
    "Staff - Counter": 39,
    "Staff - Field Enforcement": 39,
    "Staff - Back Office": 39,
    "Staff - Call Center": 22,
    "Anomalies Detected": 0
  },
  {
    "_id": "698ec0002d2b92cf4e8efcfd",
    "Month": "2025-11",
    "State": "Uttar Pradesh",
    "RTO": "UTT-RTO-3",
    "Staff - Total": 115,
    "Staff - Counter": 35,
    "Staff - Field Enforcement": 24,
    "Staff - Back Office": 44,
    "Staff - Call Center": 12,
    "Anomalies Detected": 8
  },
  {
    "_id": "698ec0002d2b92cf4e8efcfe",
    "Month": "2025-12",
    "State": "Uttar Pradesh",
    "RTO": "UTT-RTO-3",
    "Staff - Total": 180,
    "Staff - Counter": 68,
    "Staff - Field Enforcement": 45,
    "Staff - Back Office": 51,
    "Staff - Call Center": 16,
    "Anomalies Detected": 2
  },
  {
    "_id": "698ec0002d2b92cf4e8efcff",
    "Month": "2026-01",
    "State": "Uttar Pradesh",
    "RTO": "UTT-RTO-3",
    "Staff - Total": 135,
    "Staff - Counter": 40,
    "Staff - Field Enforcement": 33,
    "Staff - Back Office": 35,
    "Staff - Call Center": 27,
    "Anomalies Detected": 6
  },
  {
    "_id": "698ec0002d2b92cf4e8efd00",
    "Month": "2025-04",
    "State": "Rajasthan",
    "RTO": "RAJ-RTO-1",
    "Staff - Total": 142,
    "Staff - Counter": 54,
    "Staff - Field Enforcement": 36,
    "Staff - Back Office": 35,
    "Staff - Call Center": 17,
    "Anomalies Detected": 9
  },
  {
    "_id": "698ec0002d2b92cf4e8efd01",
    "Month": "2025-05",
    "State": "Rajasthan",
    "RTO": "RAJ-RTO-1",
    "Staff - Total": 125,
    "Staff - Counter": 43,
    "Staff - Field Enforcement": 29,
    "Staff - Back Office": 41,
    "Staff - Call Center": 12,
    "Anomalies Detected": 9
  },
  {
    "_id": "698ec0002d2b92cf4e8efd02",
    "Month": "2025-06",
    "State": "Rajasthan",
    "RTO": "RAJ-RTO-1",
    "Staff - Total": 215,
    "Staff - Counter": 69,
    "Staff - Field Enforcement": 61,
    "Staff - Back Office": 64,
    "Staff - Call Center": 21,
    "Anomalies Detected": 8
  },
  {
    "_id": "698ec0002d2b92cf4e8efd03",
    "Month": "2025-07",
    "State": "Rajasthan",
    "RTO": "RAJ-RTO-1",
    "Staff - Total": 68,
    "Staff - Counter": 21,
    "Staff - Field Enforcement": 21,
    "Staff - Back Office": 17,
    "Staff - Call Center": 9,
    "Anomalies Detected": 4
  },
  {
    "_id": "698ec0002d2b92cf4e8efd04",
    "Month": "2025-08",
    "State": "Rajasthan",
    "RTO": "RAJ-RTO-1",
    "Staff - Total": 219,
    "Staff - Counter": 73,
    "Staff - Field Enforcement": 60,
    "Staff - Back Office": 69,
    "Staff - Call Center": 17,
    "Anomalies Detected": 4
  },
  {
    "_id": "698ec0002d2b92cf4e8efd05",
    "Month": "2025-09",
    "State": "Rajasthan",
    "RTO": "RAJ-RTO-1",
    "Staff - Total": 154,
    "Staff - Counter": 60,
    "Staff - Field Enforcement": 41,
    "Staff - Back Office": 44,
    "Staff - Call Center": 9,
    "Anomalies Detected": 10
  },
  {
    "_id": "698ec0002d2b92cf4e8efd06",
    "Month": "2025-10",
    "State": "Rajasthan",
    "RTO": "RAJ-RTO-1",
    "Staff - Total": 203,
    "Staff - Counter": 72,
    "Staff - Field Enforcement": 47,
    "Staff - Back Office": 60,
    "Staff - Call Center": 24,
    "Anomalies Detected": 1
  },
  {
    "_id": "698ec0002d2b92cf4e8efd07",
    "Month": "2025-11",
    "State": "Rajasthan",
    "RTO": "RAJ-RTO-1",
    "Staff - Total": 206,
    "Staff - Counter": 63,
    "Staff - Field Enforcement": 50,
    "Staff - Back Office": 60,
    "Staff - Call Center": 33,
    "Anomalies Detected": 7
  },
  {
    "_id": "698ec0002d2b92cf4e8efd08",
    "Month": "2025-12",
    "State": "Rajasthan",
    "RTO": "RAJ-RTO-1",
    "Staff - Total": 125,
    "Staff - Counter": 34,
    "Staff - Field Enforcement": 29,
    "Staff - Back Office": 35,
    "Staff - Call Center": 27,
    "Anomalies Detected": 12
  },
  {
    "_id": "698ec0002d2b92cf4e8efd09",
    "Month": "2026-01",
    "State": "Rajasthan",
    "RTO": "RAJ-RTO-1",
    "Staff - Total": 228,
    "Staff - Counter": 79,
    "Staff - Field Enforcement": 64,
    "Staff - Back Office": 71,
    "Staff - Call Center": 14,
    "Anomalies Detected": 4
  },
  {
    "_id": "698ec0002d2b92cf4e8efd0a",
    "Month": "2025-04",
    "State": "Rajasthan",
    "RTO": "RAJ-RTO-2",
    "Staff - Total": 226,
    "Staff - Counter": 80,
    "Staff - Field Enforcement": 55,
    "Staff - Back Office": 72,
    "Staff - Call Center": 19,
    "Anomalies Detected": 10
  },
  {
    "_id": "698ec0002d2b92cf4e8efd0b",
    "Month": "2025-05",
    "State": "Rajasthan",
    "RTO": "RAJ-RTO-2",
    "Staff - Total": 88,
    "Staff - Counter": 26,
    "Staff - Field Enforcement": 23,
    "Staff - Back Office": 32,
    "Staff - Call Center": 7,
    "Anomalies Detected": 12
  },
  {
    "_id": "698ec0002d2b92cf4e8efd0c",
    "Month": "2025-06",
    "State": "Rajasthan",
    "RTO": "RAJ-RTO-2",
    "Staff - Total": 120,
    "Staff - Counter": 48,
    "Staff - Field Enforcement": 29,
    "Staff - Back Office": 26,
    "Staff - Call Center": 17,
    "Anomalies Detected": 7
  },
  {
    "_id": "698ec0002d2b92cf4e8efd0d",
    "Month": "2025-07",
    "State": "Rajasthan",
    "RTO": "RAJ-RTO-2",
    "Staff - Total": 121,
    "Staff - Counter": 34,
    "Staff - Field Enforcement": 30,
    "Staff - Back Office": 35,
    "Staff - Call Center": 22,
    "Anomalies Detected": 9
  },
  {
    "_id": "698ec0002d2b92cf4e8efd0e",
    "Month": "2025-08",
    "State": "Rajasthan",
    "RTO": "RAJ-RTO-2",
    "Staff - Total": 189,
    "Staff - Counter": 63,
    "Staff - Field Enforcement": 42,
    "Staff - Back Office": 54,
    "Staff - Call Center": 30,
    "Anomalies Detected": 0
  },
  {
    "_id": "698ec0002d2b92cf4e8efd0f",
    "Month": "2025-09",
    "State": "Rajasthan",
    "RTO": "RAJ-RTO-2",
    "Staff - Total": 81,
    "Staff - Counter": 29,
    "Staff - Field Enforcement": 17,
    "Staff - Back Office": 28,
    "Staff - Call Center": 7,
    "Anomalies Detected": 6
  },
  {
    "_id": "698ec0002d2b92cf4e8efd10",
    "Month": "2025-10",
    "State": "Rajasthan",
    "RTO": "RAJ-RTO-2",
    "Staff - Total": 106,
    "Staff - Counter": 32,
    "Staff - Field Enforcement": 24,
    "Staff - Back Office": 37,
    "Staff - Call Center": 13,
    "Anomalies Detected": 7
  },
  {
    "_id": "698ec0002d2b92cf4e8efd11",
    "Month": "2025-11",
    "State": "Rajasthan",
    "RTO": "RAJ-RTO-2",
    "Staff - Total": 67,
    "Staff - Counter": 19,
    "Staff - Field Enforcement": 20,
    "Staff - Back Office": 30,
    "Staff - Call Center": 3,
    "Anomalies Detected": 3
  },
  {
    "_id": "698ec0002d2b92cf4e8efd12",
    "Month": "2025-12",
    "State": "Rajasthan",
    "RTO": "RAJ-RTO-2",
    "Staff - Total": 194,
    "Staff - Counter": 74,
    "Staff - Field Enforcement": 52,
    "Staff - Back Office": 55,
    "Staff - Call Center": 13,
    "Anomalies Detected": 10
  },
  {
    "_id": "698ec0002d2b92cf4e8efd13",
    "Month": "2026-01",
    "State": "Rajasthan",
    "RTO": "RAJ-RTO-2",
    "Staff - Total": 186,
    "Staff - Counter": 58,
    "Staff - Field Enforcement": 45,
    "Staff - Back Office": 52,
    "Staff - Call Center": 31,
    "Anomalies Detected": 1
  },
  {
    "_id": "698ec0002d2b92cf4e8efd14",
    "Month": "2025-04",
    "State": "Rajasthan",
    "RTO": "RAJ-RTO-3",
    "Staff - Total": 212,
    "Staff - Counter": 70,
    "Staff - Field Enforcement": 51,
    "Staff - Back Office": 66,
    "Staff - Call Center": 25,
    "Anomalies Detected": 7
  },
  {
    "_id": "698ec0002d2b92cf4e8efd15",
    "Month": "2025-05",
    "State": "Rajasthan",
    "RTO": "RAJ-RTO-3",
    "Staff - Total": 240,
    "Staff - Counter": 74,
    "Staff - Field Enforcement": 57,
    "Staff - Back Office": 64,
    "Staff - Call Center": 45,
    "Anomalies Detected": 3
  },
  {
    "_id": "698ec0002d2b92cf4e8efd16",
    "Month": "2025-06",
    "State": "Rajasthan",
    "RTO": "RAJ-RTO-3",
    "Staff - Total": 66,
    "Staff - Counter": 25,
    "Staff - Field Enforcement": 17,
    "Staff - Back Office": 15,
    "Staff - Call Center": 9,
    "Anomalies Detected": 8
  },
  {
    "_id": "698ec0002d2b92cf4e8efd17",
    "Month": "2025-07",
    "State": "Rajasthan",
    "RTO": "RAJ-RTO-3",
    "Staff - Total": 82,
    "Staff - Counter": 26,
    "Staff - Field Enforcement": 15,
    "Staff - Back Office": 28,
    "Staff - Call Center": 13,
    "Anomalies Detected": 3
  },
  {
    "_id": "698ec0002d2b92cf4e8efd18",
    "Month": "2025-08",
    "State": "Rajasthan",
    "RTO": "RAJ-RTO-3",
    "Staff - Total": 75,
    "Staff - Counter": 30,
    "Staff - Field Enforcement": 16,
    "Staff - Back Office": 28,
    "Staff - Call Center": 3,
    "Anomalies Detected": 0
  },
  {
    "_id": "698ec0002d2b92cf4e8efd19",
    "Month": "2025-09",
    "State": "Rajasthan",
    "RTO": "RAJ-RTO-3",
    "Staff - Total": 108,
    "Staff - Counter": 41,
    "Staff - Field Enforcement": 24,
    "Staff - Back Office": 31,
    "Staff - Call Center": 12,
    "Anomalies Detected": 9
  },
  {
    "_id": "698ec0002d2b92cf4e8efd1a",
    "Month": "2025-10",
    "State": "Rajasthan",
    "RTO": "RAJ-RTO-3",
    "Staff - Total": 136,
    "Staff - Counter": 46,
    "Staff - Field Enforcement": 34,
    "Staff - Back Office": 38,
    "Staff - Call Center": 18,
    "Anomalies Detected": 1
  },
  {
    "_id": "698ec0002d2b92cf4e8efd1b",
    "Month": "2025-11",
    "State": "Rajasthan",
    "RTO": "RAJ-RTO-3",
    "Staff - Total": 144,
    "Staff - Counter": 44,
    "Staff - Field Enforcement": 33,
    "Staff - Back Office": 38,
    "Staff - Call Center": 29,
    "Anomalies Detected": 7
  },
  {
    "_id": "698ec0002d2b92cf4e8efd1c",
    "Month": "2025-12",
    "State": "Rajasthan",
    "RTO": "RAJ-RTO-3",
    "Staff - Total": 124,
    "Staff - Counter": 48,
    "Staff - Field Enforcement": 36,
    "Staff - Back Office": 33,
    "Staff - Call Center": 7,
    "Anomalies Detected": 4
  },
  {
    "_id": "698ec0002d2b92cf4e8efd1d",
    "Month": "2026-01",
    "State": "Rajasthan",
    "RTO": "RAJ-RTO-3",
    "Staff - Total": 150,
    "Staff - Counter": 46,
    "Staff - Field Enforcement": 42,
    "Staff - Back Office": 50,
    "Staff - Call Center": 12,
    "Anomalies Detected": 12
  },
  {
    "_id": "698ec0002d2b92cf4e8efd1e",
    "Month": "2025-04",
    "State": "Madhya Pradesh",
    "RTO": "MAD-RTO-1",
    "Staff - Total": 63,
    "Staff - Counter": 15,
    "Staff - Field Enforcement": 10,
    "Staff - Back Office": 19,
    "Staff - Call Center": 19,
    "Anomalies Detected": 6
  },
  {
    "_id": "698ec0002d2b92cf4e8efd1f",
    "Month": "2025-05",
    "State": "Madhya Pradesh",
    "RTO": "MAD-RTO-1",
    "Staff - Total": 186,
    "Staff - Counter": 54,
    "Staff - Field Enforcement": 45,
    "Staff - Back Office": 63,
    "Staff - Call Center": 24,
    "Anomalies Detected": 5
  },
  {
    "_id": "698ec0002d2b92cf4e8efd20",
    "Month": "2025-06",
    "State": "Madhya Pradesh",
    "RTO": "MAD-RTO-1",
    "Staff - Total": 190,
    "Staff - Counter": 73,
    "Staff - Field Enforcement": 50,
    "Staff - Back Office": 51,
    "Staff - Call Center": 16,
    "Anomalies Detected": 11
  },
  {
    "_id": "698ec0002d2b92cf4e8efd21",
    "Month": "2025-07",
    "State": "Madhya Pradesh",
    "RTO": "MAD-RTO-1",
    "Staff - Total": 163,
    "Staff - Counter": 56,
    "Staff - Field Enforcement": 36,
    "Staff - Back Office": 44,
    "Staff - Call Center": 27,
    "Anomalies Detected": 8
  },
  {
    "_id": "698ec0002d2b92cf4e8efd22",
    "Month": "2025-08",
    "State": "Madhya Pradesh",
    "RTO": "MAD-RTO-1",
    "Staff - Total": 74,
    "Staff - Counter": 21,
    "Staff - Field Enforcement": 22,
    "Staff - Back Office": 20,
    "Staff - Call Center": 11,
    "Anomalies Detected": 10
  },
  {
    "_id": "698ec0002d2b92cf4e8efd23",
    "Month": "2025-09",
    "State": "Madhya Pradesh",
    "RTO": "MAD-RTO-1",
    "Staff - Total": 99,
    "Staff - Counter": 37,
    "Staff - Field Enforcement": 22,
    "Staff - Back Office": 32,
    "Staff - Call Center": 8,
    "Anomalies Detected": 0
  },
  {
    "_id": "698ec0002d2b92cf4e8efd24",
    "Month": "2025-10",
    "State": "Madhya Pradesh",
    "RTO": "MAD-RTO-1",
    "Staff - Total": 201,
    "Staff - Counter": 72,
    "Staff - Field Enforcement": 40,
    "Staff - Back Office": 59,
    "Staff - Call Center": 30,
    "Anomalies Detected": 0
  },
  {
    "_id": "698ec0002d2b92cf4e8efd25",
    "Month": "2025-11",
    "State": "Madhya Pradesh",
    "RTO": "MAD-RTO-1",
    "Staff - Total": 85,
    "Staff - Counter": 32,
    "Staff - Field Enforcement": 16,
    "Staff - Back Office": 19,
    "Staff - Call Center": 18,
    "Anomalies Detected": 2
  },
  {
    "_id": "698ec0002d2b92cf4e8efd26",
    "Month": "2025-12",
    "State": "Madhya Pradesh",
    "RTO": "MAD-RTO-1",
    "Staff - Total": 236,
    "Staff - Counter": 83,
    "Staff - Field Enforcement": 50,
    "Staff - Back Office": 70,
    "Staff - Call Center": 33,
    "Anomalies Detected": 2
  },
  {
    "_id": "698ec0002d2b92cf4e8efd27",
    "Month": "2026-01",
    "State": "Madhya Pradesh",
    "RTO": "MAD-RTO-1",
    "Staff - Total": 193,
    "Staff - Counter": 66,
    "Staff - Field Enforcement": 50,
    "Staff - Back Office": 59,
    "Staff - Call Center": 18,
    "Anomalies Detected": 12
  },
  {
    "_id": "698ec0002d2b92cf4e8efd28",
    "Month": "2025-04",
    "State": "Madhya Pradesh",
    "RTO": "MAD-RTO-2",
    "Staff - Total": 235,
    "Staff - Counter": 72,
    "Staff - Field Enforcement": 59,
    "Staff - Back Office": 65,
    "Staff - Call Center": 39,
    "Anomalies Detected": 8
  },
  {
    "_id": "698ec0002d2b92cf4e8efd29",
    "Month": "2025-05",
    "State": "Madhya Pradesh",
    "RTO": "MAD-RTO-2",
    "Staff - Total": 168,
    "Staff - Counter": 61,
    "Staff - Field Enforcement": 47,
    "Staff - Back Office": 50,
    "Staff - Call Center": 10,
    "Anomalies Detected": 10
  },
  {
    "_id": "698ec0002d2b92cf4e8efd2a",
    "Month": "2025-06",
    "State": "Madhya Pradesh",
    "RTO": "MAD-RTO-2",
    "Staff - Total": 135,
    "Staff - Counter": 40,
    "Staff - Field Enforcement": 34,
    "Staff - Back Office": 40,
    "Staff - Call Center": 21,
    "Anomalies Detected": 1
  },
  {
    "_id": "698ec0002d2b92cf4e8efd2b",
    "Month": "2025-07",
    "State": "Madhya Pradesh",
    "RTO": "MAD-RTO-2",
    "Staff - Total": 110,
    "Staff - Counter": 35,
    "Staff - Field Enforcement": 26,
    "Staff - Back Office": 38,
    "Staff - Call Center": 11,
    "Anomalies Detected": 8
  },
  {
    "_id": "698ec0002d2b92cf4e8efd2c",
    "Month": "2025-08",
    "State": "Madhya Pradesh",
    "RTO": "MAD-RTO-2",
    "Staff - Total": 182,
    "Staff - Counter": 58,
    "Staff - Field Enforcement": 55,
    "Staff - Back Office": 49,
    "Staff - Call Center": 20,
    "Anomalies Detected": 6
  },
  {
    "_id": "698ec0002d2b92cf4e8efd2d",
    "Month": "2025-09",
    "State": "Madhya Pradesh",
    "RTO": "MAD-RTO-2",
    "Staff - Total": 129,
    "Staff - Counter": 46,
    "Staff - Field Enforcement": 33,
    "Staff - Back Office": 37,
    "Staff - Call Center": 13,
    "Anomalies Detected": 8
  },
  {
    "_id": "698ec0002d2b92cf4e8efd2e",
    "Month": "2025-10",
    "State": "Madhya Pradesh",
    "RTO": "MAD-RTO-2",
    "Staff - Total": 104,
    "Staff - Counter": 35,
    "Staff - Field Enforcement": 21,
    "Staff - Back Office": 41,
    "Staff - Call Center": 7,
    "Anomalies Detected": 10
  },
  {
    "_id": "698ec0002d2b92cf4e8efd2f",
    "Month": "2025-11",
    "State": "Madhya Pradesh",
    "RTO": "MAD-RTO-2",
    "Staff - Total": 135,
    "Staff - Counter": 50,
    "Staff - Field Enforcement": 32,
    "Staff - Back Office": 38,
    "Staff - Call Center": 15,
    "Anomalies Detected": 11
  },
  {
    "_id": "698ec0002d2b92cf4e8efd30",
    "Month": "2025-12",
    "State": "Madhya Pradesh",
    "RTO": "MAD-RTO-2",
    "Staff - Total": 141,
    "Staff - Counter": 41,
    "Staff - Field Enforcement": 34,
    "Staff - Back Office": 40,
    "Staff - Call Center": 26,
    "Anomalies Detected": 12
  },
  {
    "_id": "698ec0002d2b92cf4e8efd31",
    "Month": "2026-01",
    "State": "Madhya Pradesh",
    "RTO": "MAD-RTO-2",
    "Staff - Total": 207,
    "Staff - Counter": 66,
    "Staff - Field Enforcement": 49,
    "Staff - Back Office": 57,
    "Staff - Call Center": 35,
    "Anomalies Detected": 12
  },
  {
    "_id": "698ec0002d2b92cf4e8efd32",
    "Month": "2025-04",
    "State": "Madhya Pradesh",
    "RTO": "MAD-RTO-3",
    "Staff - Total": 108,
    "Staff - Counter": 33,
    "Staff - Field Enforcement": 29,
    "Staff - Back Office": 37,
    "Staff - Call Center": 9,
    "Anomalies Detected": 1
  },
  {
    "_id": "698ec0002d2b92cf4e8efd33",
    "Month": "2025-05",
    "State": "Madhya Pradesh",
    "RTO": "MAD-RTO-3",
    "Staff - Total": 122,
    "Staff - Counter": 35,
    "Staff - Field Enforcement": 25,
    "Staff - Back Office": 40,
    "Staff - Call Center": 22,
    "Anomalies Detected": 1
  },
  {
    "_id": "698ec0002d2b92cf4e8efd34",
    "Month": "2025-06",
    "State": "Madhya Pradesh",
    "RTO": "MAD-RTO-3",
    "Staff - Total": 240,
    "Staff - Counter": 85,
    "Staff - Field Enforcement": 60,
    "Staff - Back Office": 73,
    "Staff - Call Center": 22,
    "Anomalies Detected": 7
  },
  {
    "_id": "698ec0002d2b92cf4e8efd35",
    "Month": "2025-07",
    "State": "Madhya Pradesh",
    "RTO": "MAD-RTO-3",
    "Staff - Total": 205,
    "Staff - Counter": 67,
    "Staff - Field Enforcement": 47,
    "Staff - Back Office": 65,
    "Staff - Call Center": 26,
    "Anomalies Detected": 10
  },
  {
    "_id": "698ec0002d2b92cf4e8efd36",
    "Month": "2025-08",
    "State": "Madhya Pradesh",
    "RTO": "MAD-RTO-3",
    "Staff - Total": 133,
    "Staff - Counter": 32,
    "Staff - Field Enforcement": 35,
    "Staff - Back Office": 34,
    "Staff - Call Center": 32,
    "Anomalies Detected": 10
  },
  {
    "_id": "698ec0002d2b92cf4e8efd37",
    "Month": "2025-09",
    "State": "Madhya Pradesh",
    "RTO": "MAD-RTO-3",
    "Staff - Total": 75,
    "Staff - Counter": 33,
    "Staff - Field Enforcement": 18,
    "Staff - Back Office": 27,
    "Staff - Call Center": 3,
    "Anomalies Detected": 8
  },
  {
    "_id": "698ec0002d2b92cf4e8efd38",
    "Month": "2025-10",
    "State": "Madhya Pradesh",
    "RTO": "MAD-RTO-3",
    "Staff - Total": 152,
    "Staff - Counter": 61,
    "Staff - Field Enforcement": 33,
    "Staff - Back Office": 45,
    "Staff - Call Center": 13,
    "Anomalies Detected": 9
  },
  {
    "_id": "698ec0002d2b92cf4e8efd39",
    "Month": "2025-11",
    "State": "Madhya Pradesh",
    "RTO": "MAD-RTO-3",
    "Staff - Total": 178,
    "Staff - Counter": 61,
    "Staff - Field Enforcement": 49,
    "Staff - Back Office": 51,
    "Staff - Call Center": 17,
    "Anomalies Detected": 2
  },
  {
    "_id": "698ec0002d2b92cf4e8efd3a",
    "Month": "2025-12",
    "State": "Madhya Pradesh",
    "RTO": "MAD-RTO-3",
    "Staff - Total": 139,
    "Staff - Counter": 59,
    "Staff - Field Enforcement": 35,
    "Staff - Back Office": 44,
    "Staff - Call Center": 3,
    "Anomalies Detected": 3
  },
  {
    "_id": "698ec0002d2b92cf4e8efd3b",
    "Month": "2026-01",
    "State": "Madhya Pradesh",
    "RTO": "MAD-RTO-3",
    "Staff - Total": 120,
    "Staff - Counter": 36,
    "Staff - Field Enforcement": 24,
    "Staff - Back Office": 42,
    "Staff - Call Center": 18,
    "Anomalies Detected": 12
  },
  {
    "_id": "698ec0002d2b92cf4e8efd3c",
    "Month": "2025-04",
    "State": "West Bengal",
    "RTO": "WES-RTO-1",
    "Staff - Total": 86,
    "Staff - Counter": 28,
    "Staff - Field Enforcement": 21,
    "Staff - Back Office": 13,
    "Staff - Call Center": 24,
    "Anomalies Detected": 7
  },
  {
    "_id": "698ec0002d2b92cf4e8efd3d",
    "Month": "2025-05",
    "State": "West Bengal",
    "RTO": "WES-RTO-1",
    "Staff - Total": 200,
    "Staff - Counter": 66,
    "Staff - Field Enforcement": 53,
    "Staff - Back Office": 64,
    "Staff - Call Center": 17,
    "Anomalies Detected": 5
  },
  {
    "_id": "698ec0002d2b92cf4e8efd3e",
    "Month": "2025-06",
    "State": "West Bengal",
    "RTO": "WES-RTO-1",
    "Staff - Total": 162,
    "Staff - Counter": 58,
    "Staff - Field Enforcement": 34,
    "Staff - Back Office": 51,
    "Staff - Call Center": 19,
    "Anomalies Detected": 2
  },
  {
    "_id": "698ec0002d2b92cf4e8efd3f",
    "Month": "2025-07",
    "State": "West Bengal",
    "RTO": "WES-RTO-1",
    "Staff - Total": 136,
    "Staff - Counter": 53,
    "Staff - Field Enforcement": 42,
    "Staff - Back Office": 32,
    "Staff - Call Center": 9,
    "Anomalies Detected": 12
  },
  {
    "_id": "698ec0002d2b92cf4e8efd40",
    "Month": "2025-08",
    "State": "West Bengal",
    "RTO": "WES-RTO-1",
    "Staff - Total": 113,
    "Staff - Counter": 35,
    "Staff - Field Enforcement": 28,
    "Staff - Back Office": 33,
    "Staff - Call Center": 17,
    "Anomalies Detected": 7
  },
  {
    "_id": "698ec0002d2b92cf4e8efd41",
    "Month": "2025-09",
    "State": "West Bengal",
    "RTO": "WES-RTO-1",
    "Staff - Total": 232,
    "Staff - Counter": 86,
    "Staff - Field Enforcement": 53,
    "Staff - Back Office": 64,
    "Staff - Call Center": 29,
    "Anomalies Detected": 11
  },
  {
    "_id": "698ec0002d2b92cf4e8efd42",
    "Month": "2025-10",
    "State": "West Bengal",
    "RTO": "WES-RTO-1",
    "Staff - Total": 66,
    "Staff - Counter": 21,
    "Staff - Field Enforcement": 11,
    "Staff - Back Office": 19,
    "Staff - Call Center": 15,
    "Anomalies Detected": 7
  },
  {
    "_id": "698ec0002d2b92cf4e8efd43",
    "Month": "2025-11",
    "State": "West Bengal",
    "RTO": "WES-RTO-1",
    "Staff - Total": 77,
    "Staff - Counter": 23,
    "Staff - Field Enforcement": 22,
    "Staff - Back Office": 22,
    "Staff - Call Center": 10,
    "Anomalies Detected": 8
  },
  {
    "_id": "698ec0002d2b92cf4e8efd44",
    "Month": "2025-12",
    "State": "West Bengal",
    "RTO": "WES-RTO-1",
    "Staff - Total": 139,
    "Staff - Counter": 47,
    "Staff - Field Enforcement": 34,
    "Staff - Back Office": 38,
    "Staff - Call Center": 20,
    "Anomalies Detected": 12
  },
  {
    "_id": "698ec0002d2b92cf4e8efd45",
    "Month": "2026-01",
    "State": "West Bengal",
    "RTO": "WES-RTO-1",
    "Staff - Total": 214,
    "Staff - Counter": 78,
    "Staff - Field Enforcement": 51,
    "Staff - Back Office": 66,
    "Staff - Call Center": 19,
    "Anomalies Detected": 1
  },
  {
    "_id": "698ec0002d2b92cf4e8efd46",
    "Month": "2025-04",
    "State": "West Bengal",
    "RTO": "WES-RTO-2",
    "Staff - Total": 236,
    "Staff - Counter": 86,
    "Staff - Field Enforcement": 56,
    "Staff - Back Office": 75,
    "Staff - Call Center": 19,
    "Anomalies Detected": 2
  },
  {
    "_id": "698ec0002d2b92cf4e8efd47",
    "Month": "2025-05",
    "State": "West Bengal",
    "RTO": "WES-RTO-2",
    "Staff - Total": 196,
    "Staff - Counter": 76,
    "Staff - Field Enforcement": 44,
    "Staff - Back Office": 51,
    "Staff - Call Center": 25,
    "Anomalies Detected": 0
  },
  {
    "_id": "698ec0002d2b92cf4e8efd48",
    "Month": "2025-06",
    "State": "West Bengal",
    "RTO": "WES-RTO-2",
    "Staff - Total": 169,
    "Staff - Counter": 52,
    "Staff - Field Enforcement": 36,
    "Staff - Back Office": 53,
    "Staff - Call Center": 28,
    "Anomalies Detected": 2
  },
  {
    "_id": "698ec0002d2b92cf4e8efd49",
    "Month": "2025-07",
    "State": "West Bengal",
    "RTO": "WES-RTO-2",
    "Staff - Total": 200,
    "Staff - Counter": 67,
    "Staff - Field Enforcement": 48,
    "Staff - Back Office": 57,
    "Staff - Call Center": 28,
    "Anomalies Detected": 1
  },
  {
    "_id": "698ec0002d2b92cf4e8efd4a",
    "Month": "2025-08",
    "State": "West Bengal",
    "RTO": "WES-RTO-2",
    "Staff - Total": 164,
    "Staff - Counter": 53,
    "Staff - Field Enforcement": 35,
    "Staff - Back Office": 53,
    "Staff - Call Center": 23,
    "Anomalies Detected": 6
  },
  {
    "_id": "698ec0002d2b92cf4e8efd4b",
    "Month": "2025-09",
    "State": "West Bengal",
    "RTO": "WES-RTO-2",
    "Staff - Total": 79,
    "Staff - Counter": 37,
    "Staff - Field Enforcement": 17,
    "Staff - Back Office": 27,
    "Staff - Call Center": 3,
    "Anomalies Detected": 3
  },
  {
    "_id": "698ec0002d2b92cf4e8efd4c",
    "Month": "2025-10",
    "State": "West Bengal",
    "RTO": "WES-RTO-2",
    "Staff - Total": 140,
    "Staff - Counter": 46,
    "Staff - Field Enforcement": 32,
    "Staff - Back Office": 45,
    "Staff - Call Center": 17,
    "Anomalies Detected": 1
  },
  {
    "_id": "698ec0002d2b92cf4e8efd4d",
    "Month": "2025-11",
    "State": "West Bengal",
    "RTO": "WES-RTO-2",
    "Staff - Total": 202,
    "Staff - Counter": 63,
    "Staff - Field Enforcement": 45,
    "Staff - Back Office": 47,
    "Staff - Call Center": 47,
    "Anomalies Detected": 2
  },
  {
    "_id": "698ec0002d2b92cf4e8efd4e",
    "Month": "2025-12",
    "State": "West Bengal",
    "RTO": "WES-RTO-2",
    "Staff - Total": 100,
    "Staff - Counter": 33,
    "Staff - Field Enforcement": 24,
    "Staff - Back Office": 21,
    "Staff - Call Center": 22,
    "Anomalies Detected": 9
  },
  {
    "_id": "698ec0002d2b92cf4e8efd4f",
    "Month": "2026-01",
    "State": "West Bengal",
    "RTO": "WES-RTO-2",
    "Staff - Total": 94,
    "Staff - Counter": 30,
    "Staff - Field Enforcement": 20,
    "Staff - Back Office": 28,
    "Staff - Call Center": 16,
    "Anomalies Detected": 7
  },
  {
    "_id": "698ec0002d2b92cf4e8efd50",
    "Month": "2025-04",
    "State": "West Bengal",
    "RTO": "WES-RTO-3",
    "Staff - Total": 224,
    "Staff - Counter": 89,
    "Staff - Field Enforcement": 55,
    "Staff - Back Office": 72,
    "Staff - Call Center": 8,
    "Anomalies Detected": 12
  },
  {
    "_id": "698ec0002d2b92cf4e8efd51",
    "Month": "2025-05",
    "State": "West Bengal",
    "RTO": "WES-RTO-3",
    "Staff - Total": 100,
    "Staff - Counter": 26,
    "Staff - Field Enforcement": 23,
    "Staff - Back Office": 22,
    "Staff - Call Center": 29,
    "Anomalies Detected": 7
  },
  {
    "_id": "698ec0002d2b92cf4e8efd52",
    "Month": "2025-06",
    "State": "West Bengal",
    "RTO": "WES-RTO-3",
    "Staff - Total": 127,
    "Staff - Counter": 40,
    "Staff - Field Enforcement": 23,
    "Staff - Back Office": 46,
    "Staff - Call Center": 18,
    "Anomalies Detected": 4
  },
  {
    "_id": "698ec0002d2b92cf4e8efd53",
    "Month": "2025-07",
    "State": "West Bengal",
    "RTO": "WES-RTO-3",
    "Staff - Total": 229,
    "Staff - Counter": 71,
    "Staff - Field Enforcement": 60,
    "Staff - Back Office": 65,
    "Staff - Call Center": 33,
    "Anomalies Detected": 12
  },
  {
    "_id": "698ec0002d2b92cf4e8efd54",
    "Month": "2025-08",
    "State": "West Bengal",
    "RTO": "WES-RTO-3",
    "Staff - Total": 98,
    "Staff - Counter": 30,
    "Staff - Field Enforcement": 22,
    "Staff - Back Office": 31,
    "Staff - Call Center": 15,
    "Anomalies Detected": 7
  },
  {
    "_id": "698ec0002d2b92cf4e8efd55",
    "Month": "2025-09",
    "State": "West Bengal",
    "RTO": "WES-RTO-3",
    "Staff - Total": 63,
    "Staff - Counter": 25,
    "Staff - Field Enforcement": 15,
    "Staff - Back Office": 21,
    "Staff - Call Center": 3,
    "Anomalies Detected": 10
  },
  {
    "_id": "698ec0002d2b92cf4e8efd56",
    "Month": "2025-10",
    "State": "West Bengal",
    "RTO": "WES-RTO-3",
    "Staff - Total": 114,
    "Staff - Counter": 40,
    "Staff - Field Enforcement": 27,
    "Staff - Back Office": 26,
    "Staff - Call Center": 21,
    "Anomalies Detected": 7
  },
  {
    "_id": "698ec0002d2b92cf4e8efd57",
    "Month": "2025-11",
    "State": "West Bengal",
    "RTO": "WES-RTO-3",
    "Staff - Total": 89,
    "Staff - Counter": 31,
    "Staff - Field Enforcement": 20,
    "Staff - Back Office": 33,
    "Staff - Call Center": 5,
    "Anomalies Detected": 3
  },
  {
    "_id": "698ec0002d2b92cf4e8efd58",
    "Month": "2025-12",
    "State": "West Bengal",
    "RTO": "WES-RTO-3",
    "Staff - Total": 196,
    "Staff - Counter": 76,
    "Staff - Field Enforcement": 48,
    "Staff - Back Office": 60,
    "Staff - Call Center": 12,
    "Anomalies Detected": 7
  },
  {
    "_id": "698ec0002d2b92cf4e8efd59",
    "Month": "2026-01",
    "State": "West Bengal",
    "RTO": "WES-RTO-3",
    "Staff - Total": 85,
    "Staff - Counter": 21,
    "Staff - Field Enforcement": 20,
    "Staff - Back Office": 27,
    "Staff - Call Center": 17,
    "Anomalies Detected": 10
  },
  {
    "_id": "698ec0002d2b92cf4e8efd5a",
    "Month": "2025-04",
    "State": "Telangana",
    "RTO": "TEL-RTO-1",
    "Staff - Total": 184,
    "Staff - Counter": 63,
    "Staff - Field Enforcement": 37,
    "Staff - Back Office": 47,
    "Staff - Call Center": 37,
    "Anomalies Detected": 7
  },
  {
    "_id": "698ec0002d2b92cf4e8efd5b",
    "Month": "2025-05",
    "State": "Telangana",
    "RTO": "TEL-RTO-1",
    "Staff - Total": 105,
    "Staff - Counter": 31,
    "Staff - Field Enforcement": 31,
    "Staff - Back Office": 26,
    "Staff - Call Center": 17,
    "Anomalies Detected": 11
  },
  {
    "_id": "698ec0002d2b92cf4e8efd5c",
    "Month": "2025-06",
    "State": "Telangana",
    "RTO": "TEL-RTO-1",
    "Staff - Total": 183,
    "Staff - Counter": 67,
    "Staff - Field Enforcement": 42,
    "Staff - Back Office": 62,
    "Staff - Call Center": 12,
    "Anomalies Detected": 5
  },
  {
    "_id": "698ec0002d2b92cf4e8efd5d",
    "Month": "2025-07",
    "State": "Telangana",
    "RTO": "TEL-RTO-1",
    "Staff - Total": 226,
    "Staff - Counter": 81,
    "Staff - Field Enforcement": 55,
    "Staff - Back Office": 71,
    "Staff - Call Center": 19,
    "Anomalies Detected": 4
  },
  {
    "_id": "698ec0002d2b92cf4e8efd5e",
    "Month": "2025-08",
    "State": "Telangana",
    "RTO": "TEL-RTO-1",
    "Staff - Total": 222,
    "Staff - Counter": 77,
    "Staff - Field Enforcement": 62,
    "Staff - Back Office": 63,
    "Staff - Call Center": 20,
    "Anomalies Detected": 2
  },
  {
    "_id": "698ec0002d2b92cf4e8efd5f",
    "Month": "2025-09",
    "State": "Telangana",
    "RTO": "TEL-RTO-1",
    "Staff - Total": 102,
    "Staff - Counter": 38,
    "Staff - Field Enforcement": 21,
    "Staff - Back Office": 31,
    "Staff - Call Center": 12,
    "Anomalies Detected": 7
  },
  {
    "_id": "698ec0002d2b92cf4e8efd60",
    "Month": "2025-10",
    "State": "Telangana",
    "RTO": "TEL-RTO-1",
    "Staff - Total": 184,
    "Staff - Counter": 60,
    "Staff - Field Enforcement": 47,
    "Staff - Back Office": 55,
    "Staff - Call Center": 22,
    "Anomalies Detected": 8
  },
  {
    "_id": "698ec0002d2b92cf4e8efd61",
    "Month": "2025-11",
    "State": "Telangana",
    "RTO": "TEL-RTO-1",
    "Staff - Total": 212,
    "Staff - Counter": 73,
    "Staff - Field Enforcement": 52,
    "Staff - Back Office": 61,
    "Staff - Call Center": 26,
    "Anomalies Detected": 3
  },
  {
    "_id": "698ec0002d2b92cf4e8efd62",
    "Month": "2025-12",
    "State": "Telangana",
    "RTO": "TEL-RTO-1",
    "Staff - Total": 156,
    "Staff - Counter": 51,
    "Staff - Field Enforcement": 49,
    "Staff - Back Office": 39,
    "Staff - Call Center": 17,
    "Anomalies Detected": 5
  },
  {
    "_id": "698ec0002d2b92cf4e8efd63",
    "Month": "2026-01",
    "State": "Telangana",
    "RTO": "TEL-RTO-1",
    "Staff - Total": 135,
    "Staff - Counter": 44,
    "Staff - Field Enforcement": 41,
    "Staff - Back Office": 33,
    "Staff - Call Center": 17,
    "Anomalies Detected": 10
  },
  {
    "_id": "698ec0002d2b92cf4e8efd64",
    "Month": "2025-04",
    "State": "Telangana",
    "RTO": "TEL-RTO-2",
    "Staff - Total": 173,
    "Staff - Counter": 61,
    "Staff - Field Enforcement": 44,
    "Staff - Back Office": 58,
    "Staff - Call Center": 10,
    "Anomalies Detected": 12
  },
  {
    "_id": "698ec0002d2b92cf4e8efd65",
    "Month": "2025-05",
    "State": "Telangana",
    "RTO": "TEL-RTO-2",
    "Staff - Total": 142,
    "Staff - Counter": 47,
    "Staff - Field Enforcement": 36,
    "Staff - Back Office": 33,
    "Staff - Call Center": 26,
    "Anomalies Detected": 5
  },
  {
    "_id": "698ec0002d2b92cf4e8efd66",
    "Month": "2025-06",
    "State": "Telangana",
    "RTO": "TEL-RTO-2",
    "Staff - Total": 213,
    "Staff - Counter": 70,
    "Staff - Field Enforcement": 52,
    "Staff - Back Office": 55,
    "Staff - Call Center": 36,
    "Anomalies Detected": 3
  },
  {
    "_id": "698ec0002d2b92cf4e8efd67",
    "Month": "2025-07",
    "State": "Telangana",
    "RTO": "TEL-RTO-2",
    "Staff - Total": 189,
    "Staff - Counter": 57,
    "Staff - Field Enforcement": 47,
    "Staff - Back Office": 50,
    "Staff - Call Center": 35,
    "Anomalies Detected": 5
  },
  {
    "_id": "698ec0002d2b92cf4e8efd68",
    "Month": "2025-08",
    "State": "Telangana",
    "RTO": "TEL-RTO-2",
    "Staff - Total": 188,
    "Staff - Counter": 71,
    "Staff - Field Enforcement": 49,
    "Staff - Back Office": 62,
    "Staff - Call Center": 6,
    "Anomalies Detected": 5
  },
  {
    "_id": "698ec0002d2b92cf4e8efd69",
    "Month": "2025-09",
    "State": "Telangana",
    "RTO": "TEL-RTO-2",
    "Staff - Total": 101,
    "Staff - Counter": 31,
    "Staff - Field Enforcement": 31,
    "Staff - Back Office": 22,
    "Staff - Call Center": 17,
    "Anomalies Detected": 3
  },
  {
    "_id": "698ec0002d2b92cf4e8efd6a",
    "Month": "2025-10",
    "State": "Telangana",
    "RTO": "TEL-RTO-2",
    "Staff - Total": 82,
    "Staff - Counter": 26,
    "Staff - Field Enforcement": 16,
    "Staff - Back Office": 27,
    "Staff - Call Center": 13,
    "Anomalies Detected": 5
  },
  {
    "_id": "698ec0002d2b92cf4e8efd6b",
    "Month": "2025-11",
    "State": "Telangana",
    "RTO": "TEL-RTO-2",
    "Staff - Total": 121,
    "Staff - Counter": 46,
    "Staff - Field Enforcement": 31,
    "Staff - Back Office": 36,
    "Staff - Call Center": 8,
    "Anomalies Detected": 4
  },
  {
    "_id": "698ec0002d2b92cf4e8efd6c",
    "Month": "2025-12",
    "State": "Telangana",
    "RTO": "TEL-RTO-2",
    "Staff - Total": 205,
    "Staff - Counter": 73,
    "Staff - Field Enforcement": 53,
    "Staff - Back Office": 62,
    "Staff - Call Center": 17,
    "Anomalies Detected": 9
  },
  {
    "_id": "698ec0002d2b92cf4e8efd6d",
    "Month": "2026-01",
    "State": "Telangana",
    "RTO": "TEL-RTO-2",
    "Staff - Total": 87,
    "Staff - Counter": 22,
    "Staff - Field Enforcement": 21,
    "Staff - Back Office": 19,
    "Staff - Call Center": 25,
    "Anomalies Detected": 3
  },
  {
    "_id": "698ec0002d2b92cf4e8efd6e",
    "Month": "2025-04",
    "State": "Telangana",
    "RTO": "TEL-RTO-3",
    "Staff - Total": 225,
    "Staff - Counter": 86,
    "Staff - Field Enforcement": 54,
    "Staff - Back Office": 68,
    "Staff - Call Center": 17,
    "Anomalies Detected": 11
  },
  {
    "_id": "698ec0002d2b92cf4e8efd6f",
    "Month": "2025-05",
    "State": "Telangana",
    "RTO": "TEL-RTO-3",
    "Staff - Total": 163,
    "Staff - Counter": 46,
    "Staff - Field Enforcement": 38,
    "Staff - Back Office": 50,
    "Staff - Call Center": 29,
    "Anomalies Detected": 8
  },
  {
    "_id": "698ec0002d2b92cf4e8efd70",
    "Month": "2025-06",
    "State": "Telangana",
    "RTO": "TEL-RTO-3",
    "Staff - Total": 92,
    "Staff - Counter": 27,
    "Staff - Field Enforcement": 27,
    "Staff - Back Office": 32,
    "Staff - Call Center": 6,
    "Anomalies Detected": 12
  },
  {
    "_id": "698ec0002d2b92cf4e8efd71",
    "Month": "2025-07",
    "State": "Telangana",
    "RTO": "TEL-RTO-3",
    "Staff - Total": 147,
    "Staff - Counter": 55,
    "Staff - Field Enforcement": 37,
    "Staff - Back Office": 46,
    "Staff - Call Center": 9,
    "Anomalies Detected": 2
  },
  {
    "_id": "698ec0002d2b92cf4e8efd72",
    "Month": "2025-08",
    "State": "Telangana",
    "RTO": "TEL-RTO-3",
    "Staff - Total": 153,
    "Staff - Counter": 54,
    "Staff - Field Enforcement": 35,
    "Staff - Back Office": 52,
    "Staff - Call Center": 12,
    "Anomalies Detected": 5
  },
  {
    "_id": "698ec0002d2b92cf4e8efd73",
    "Month": "2025-09",
    "State": "Telangana",
    "RTO": "TEL-RTO-3",
    "Staff - Total": 72,
    "Staff - Counter": 32,
    "Staff - Field Enforcement": 16,
    "Staff - Back Office": 16,
    "Staff - Call Center": 8,
    "Anomalies Detected": 8
  },
  {
    "_id": "698ec0002d2b92cf4e8efd74",
    "Month": "2025-10",
    "State": "Telangana",
    "RTO": "TEL-RTO-3",
    "Staff - Total": 151,
    "Staff - Counter": 55,
    "Staff - Field Enforcement": 39,
    "Staff - Back Office": 42,
    "Staff - Call Center": 15,
    "Anomalies Detected": 4
  },
  {
    "_id": "698ec0002d2b92cf4e8efd75",
    "Month": "2025-11",
    "State": "Telangana",
    "RTO": "TEL-RTO-3",
    "Staff - Total": 227,
    "Staff - Counter": 74,
    "Staff - Field Enforcement": 59,
    "Staff - Back Office": 74,
    "Staff - Call Center": 20,
    "Anomalies Detected": 8
  },
  {
    "_id": "698ec0002d2b92cf4e8efd76",
    "Month": "2025-12",
    "State": "Telangana",
    "RTO": "TEL-RTO-3",
    "Staff - Total": 179,
    "Staff - Counter": 66,
    "Staff - Field Enforcement": 39,
    "Staff - Back Office": 54,
    "Staff - Call Center": 20,
    "Anomalies Detected": 9
  },
  {
    "_id": "698ec0002d2b92cf4e8efd77",
    "Month": "2026-01",
    "State": "Telangana",
    "RTO": "TEL-RTO-3",
    "Staff - Total": 118,
    "Staff - Counter": 36,
    "Staff - Field Enforcement": 29,
    "Staff - Back Office": 42,
    "Staff - Call Center": 11,
    "Anomalies Detected": 12
  }
]